{"url":"http:\/\/localhost:8080\/babana\/index.php\/reports","method":"POST","isAJAX":true,"startTime":1697704245.186554,"totalTime":94.3,"totalMemory":"5.473","segmentDuration":15,"segmentCount":7,"CI_VERSION":"4.3.7","collectors":[{"title":"Timers","titleSafe":"timers","titleDetails":"","display":[],"badgeValue":null,"isEmpty":false,"hasTabContent":false,"hasLabel":false,"icon":"","hasTimelineData":true,"timelineData":[{"name":"Bootstrap","component":"Timer","start":1697704245.20884,"duration":0.0195310115814209},{"name":"Routing","component":"Timer","start":1697704245.228373,"duration":7.486343383789062e-5},{"name":"Before Filters","component":"Timer","start":1697704245.230292,"duration":1.5020370483398438e-5},{"name":"Controller","component":"Timer","start":1697704245.230309,"duration":0.050572872161865234},{"name":"Controller Constructor","component":"Timer","start":1697704245.23031,"duration":0.01203608512878418},{"name":"After Filters","component":"Timer","start":1697704245.2809,"duration":0.0006799697875976562}]},{"title":"Database","titleSafe":"database","titleDetails":"(24 total Queries, 24 of them unique across 1 Connection)","display":{"queries":[{"hover":"","class":"","duration":"0.3 ms","sql":"<strong>SELECT<\/strong> <strong>COUNT<\/strong>(`bill_id`) <strong>AS<\/strong> `bill_id`\n<strong>FROM<\/strong> `bill`\n<strong>WHERE<\/strong> `status` = &#039;Done&#039;\n<strong>AND<\/strong> `date_check_out` &gt;= &#039;2023-10-19 00:00:00&#039;\n<strong>AND<\/strong> `date_check_out` &lt;= &#039;2023-10-19 15:30:45&#039;","trace":[{"file":"SYSTEMPATH\\Database\\BaseBuilder.php:1616","function":"\u00a0\u00a0\u00a0\u00a0\u00a0\u00a0\u00a0\u00a0CodeIgniter\\Database\\BaseConnection->query()","index":"\u00a0\u00a01\u00a0\u00a0\u00a0\u00a0"},{"file":"APPPATH\\Models\\BillModel.php:135","function":"\u00a0\u00a0\u00a0\u00a0\u00a0\u00a0\u00a0\u00a0CodeIgniter\\Database\\BaseBuilder->get()","index":"\u00a0\u00a02\u00a0\u00a0\u00a0\u00a0"},{"file":"APPPATH\\Controllers\\Home.php:2233","function":"\u00a0\u00a0\u00a0\u00a0\u00a0\u00a0\u00a0\u00a0App\\Models\\BillModel->isAlreadyExist()","index":"\u00a0\u00a03\u00a0\u00a0\u00a0\u00a0"},{"file":"SYSTEMPATH\\CodeIgniter.php:932","function":"\u00a0\u00a0\u00a0\u00a0\u00a0\u00a0\u00a0\u00a0App\\Controllers\\Home->reports()","index":"\u00a0\u00a04\u00a0\u00a0\u00a0\u00a0"},{"file":"SYSTEMPATH\\CodeIgniter.php:497","function":"\u00a0\u00a0\u00a0\u00a0\u00a0\u00a0\u00a0\u00a0CodeIgniter\\CodeIgniter->runController()","index":"\u00a0\u00a05\u00a0\u00a0\u00a0\u00a0"},{"file":"SYSTEMPATH\\CodeIgniter.php:366","function":"\u00a0\u00a0\u00a0\u00a0\u00a0\u00a0\u00a0\u00a0CodeIgniter\\CodeIgniter->handleRequest()","index":"\u00a0\u00a06\u00a0\u00a0\u00a0\u00a0"},{"file":"FCPATH\\index.php:68","function":"\u00a0\u00a0\u00a0\u00a0\u00a0\u00a0\u00a0\u00a0CodeIgniter\\CodeIgniter->run()","index":"\u00a0\u00a07\u00a0\u00a0\u00a0\u00a0"}],"trace-file":"APPPATH\\Models\\BillModel.php:135","qid":"bd71ce0986796b6db981a7ab0f50d48f"},{"hover":"","class":"","duration":"0.18 ms","sql":"<strong>SELECT<\/strong> *\n<strong>FROM<\/strong> `bill`\n<strong>WHERE<\/strong> `status` = &#039;Done&#039;\n<strong>AND<\/strong> `date_check_out` &gt;= &#039;2023-10-19 00:00:00&#039;\n<strong>AND<\/strong> `date_check_out` &lt;= &#039;2023-10-19 15:30:45&#039;","trace":[{"file":"SYSTEMPATH\\Database\\BaseBuilder.php:1616","function":"\u00a0\u00a0\u00a0\u00a0\u00a0\u00a0\u00a0\u00a0CodeIgniter\\Database\\BaseConnection->query()","index":"\u00a0\u00a01\u00a0\u00a0\u00a0\u00a0"},{"file":"APPPATH\\Models\\BillModel.php:102","function":"\u00a0\u00a0\u00a0\u00a0\u00a0\u00a0\u00a0\u00a0CodeIgniter\\Database\\BaseBuilder->get()","index":"\u00a0\u00a02\u00a0\u00a0\u00a0\u00a0"},{"file":"APPPATH\\Controllers\\Home.php:2235","function":"\u00a0\u00a0\u00a0\u00a0\u00a0\u00a0\u00a0\u00a0App\\Models\\BillModel->readOptions()","index":"\u00a0\u00a03\u00a0\u00a0\u00a0\u00a0"},{"file":"SYSTEMPATH\\CodeIgniter.php:932","function":"\u00a0\u00a0\u00a0\u00a0\u00a0\u00a0\u00a0\u00a0App\\Controllers\\Home->reports()","index":"\u00a0\u00a04\u00a0\u00a0\u00a0\u00a0"},{"file":"SYSTEMPATH\\CodeIgniter.php:497","function":"\u00a0\u00a0\u00a0\u00a0\u00a0\u00a0\u00a0\u00a0CodeIgniter\\CodeIgniter->runController()","index":"\u00a0\u00a05\u00a0\u00a0\u00a0\u00a0"},{"file":"SYSTEMPATH\\CodeIgniter.php:366","function":"\u00a0\u00a0\u00a0\u00a0\u00a0\u00a0\u00a0\u00a0CodeIgniter\\CodeIgniter->handleRequest()","index":"\u00a0\u00a06\u00a0\u00a0\u00a0\u00a0"},{"file":"FCPATH\\index.php:68","function":"\u00a0\u00a0\u00a0\u00a0\u00a0\u00a0\u00a0\u00a0CodeIgniter\\CodeIgniter->run()","index":"\u00a0\u00a07\u00a0\u00a0\u00a0\u00a0"}],"trace-file":"APPPATH\\Models\\BillModel.php:102","qid":"059f9e2ec25a533bc225ed195d0fb3e2"},{"hover":"","class":"","duration":"0.14 ms","sql":"<strong>SELECT<\/strong> <strong>COUNT<\/strong>(bill_id) as bill_id\n<strong>FROM<\/strong> `bill`\n<strong>WHERE<\/strong> `status` = &#039;Done&#039;\n<strong>AND<\/strong> `date_check_out` &gt;= &#039;2023-10-19 00:00:00&#039;\n<strong>AND<\/strong> `date_check_out` &lt;= &#039;2023-10-19 15:30:45&#039;","trace":[{"file":"SYSTEMPATH\\Database\\BaseBuilder.php:1616","function":"\u00a0\u00a0\u00a0\u00a0\u00a0\u00a0\u00a0\u00a0CodeIgniter\\Database\\BaseConnection->query()","index":"\u00a0\u00a01\u00a0\u00a0\u00a0\u00a0"},{"file":"APPPATH\\Models\\BillModel.php:50","function":"\u00a0\u00a0\u00a0\u00a0\u00a0\u00a0\u00a0\u00a0CodeIgniter\\Database\\BaseBuilder->get()","index":"\u00a0\u00a02\u00a0\u00a0\u00a0\u00a0"},{"file":"APPPATH\\Controllers\\Home.php:2238","function":"\u00a0\u00a0\u00a0\u00a0\u00a0\u00a0\u00a0\u00a0App\\Models\\BillModel->countOptions()","index":"\u00a0\u00a03\u00a0\u00a0\u00a0\u00a0"},{"file":"SYSTEMPATH\\CodeIgniter.php:932","function":"\u00a0\u00a0\u00a0\u00a0\u00a0\u00a0\u00a0\u00a0App\\Controllers\\Home->reports()","index":"\u00a0\u00a04\u00a0\u00a0\u00a0\u00a0"},{"file":"SYSTEMPATH\\CodeIgniter.php:497","function":"\u00a0\u00a0\u00a0\u00a0\u00a0\u00a0\u00a0\u00a0CodeIgniter\\CodeIgniter->runController()","index":"\u00a0\u00a05\u00a0\u00a0\u00a0\u00a0"},{"file":"SYSTEMPATH\\CodeIgniter.php:366","function":"\u00a0\u00a0\u00a0\u00a0\u00a0\u00a0\u00a0\u00a0CodeIgniter\\CodeIgniter->handleRequest()","index":"\u00a0\u00a06\u00a0\u00a0\u00a0\u00a0"},{"file":"FCPATH\\index.php:68","function":"\u00a0\u00a0\u00a0\u00a0\u00a0\u00a0\u00a0\u00a0CodeIgniter\\CodeIgniter->run()","index":"\u00a0\u00a07\u00a0\u00a0\u00a0\u00a0"}],"trace-file":"APPPATH\\Models\\BillModel.php:50","qid":"5531df34e78d1a46586750e93ae0b370"},{"hover":"","class":"","duration":"0.19 ms","sql":"<strong>SELECT<\/strong> <strong>SUM<\/strong>(sum_orders) as sum_orders\n<strong>FROM<\/strong> `bill`\n<strong>WHERE<\/strong> `status` = &#039;Done&#039;\n<strong>AND<\/strong> `date_check_out` &gt;= &#039;2023-10-19 00:00:00&#039;\n<strong>AND<\/strong> `date_check_out` &lt;= &#039;2023-10-19 15:30:45&#039;","trace":[{"file":"SYSTEMPATH\\Database\\BaseBuilder.php:1616","function":"\u00a0\u00a0\u00a0\u00a0\u00a0\u00a0\u00a0\u00a0CodeIgniter\\Database\\BaseConnection->query()","index":"\u00a0\u00a01\u00a0\u00a0\u00a0\u00a0"},{"file":"APPPATH\\Models\\BillModel.php:60","function":"\u00a0\u00a0\u00a0\u00a0\u00a0\u00a0\u00a0\u00a0CodeIgniter\\Database\\BaseBuilder->get()","index":"\u00a0\u00a02\u00a0\u00a0\u00a0\u00a0"},{"file":"APPPATH\\Controllers\\Home.php:2241","function":"\u00a0\u00a0\u00a0\u00a0\u00a0\u00a0\u00a0\u00a0App\\Models\\BillModel->sumOptions()","index":"\u00a0\u00a03\u00a0\u00a0\u00a0\u00a0"},{"file":"SYSTEMPATH\\CodeIgniter.php:932","function":"\u00a0\u00a0\u00a0\u00a0\u00a0\u00a0\u00a0\u00a0App\\Controllers\\Home->reports()","index":"\u00a0\u00a04\u00a0\u00a0\u00a0\u00a0"},{"file":"SYSTEMPATH\\CodeIgniter.php:497","function":"\u00a0\u00a0\u00a0\u00a0\u00a0\u00a0\u00a0\u00a0CodeIgniter\\CodeIgniter->runController()","index":"\u00a0\u00a05\u00a0\u00a0\u00a0\u00a0"},{"file":"SYSTEMPATH\\CodeIgniter.php:366","function":"\u00a0\u00a0\u00a0\u00a0\u00a0\u00a0\u00a0\u00a0CodeIgniter\\CodeIgniter->handleRequest()","index":"\u00a0\u00a06\u00a0\u00a0\u00a0\u00a0"},{"file":"FCPATH\\index.php:68","function":"\u00a0\u00a0\u00a0\u00a0\u00a0\u00a0\u00a0\u00a0CodeIgniter\\CodeIgniter->run()","index":"\u00a0\u00a07\u00a0\u00a0\u00a0\u00a0"}],"trace-file":"APPPATH\\Models\\BillModel.php:60","qid":"cd35c10600773086dc421b46acd8f9eb"},{"hover":"","class":"","duration":"0.17 ms","sql":"<strong>SELECT<\/strong> <strong>SUM<\/strong>(total) as total\n<strong>FROM<\/strong> `bill`\n<strong>WHERE<\/strong> `status` = &#039;Done&#039;\n<strong>AND<\/strong> `date_check_out` &gt;= &#039;2023-10-19 00:00:00&#039;\n<strong>AND<\/strong> `date_check_out` &lt;= &#039;2023-10-19 15:30:45&#039;","trace":[{"file":"SYSTEMPATH\\Database\\BaseBuilder.php:1616","function":"\u00a0\u00a0\u00a0\u00a0\u00a0\u00a0\u00a0\u00a0CodeIgniter\\Database\\BaseConnection->query()","index":"\u00a0\u00a01\u00a0\u00a0\u00a0\u00a0"},{"file":"APPPATH\\Models\\BillModel.php:60","function":"\u00a0\u00a0\u00a0\u00a0\u00a0\u00a0\u00a0\u00a0CodeIgniter\\Database\\BaseBuilder->get()","index":"\u00a0\u00a02\u00a0\u00a0\u00a0\u00a0"},{"file":"APPPATH\\Controllers\\Home.php:2244","function":"\u00a0\u00a0\u00a0\u00a0\u00a0\u00a0\u00a0\u00a0App\\Models\\BillModel->sumOptions()","index":"\u00a0\u00a03\u00a0\u00a0\u00a0\u00a0"},{"file":"SYSTEMPATH\\CodeIgniter.php:932","function":"\u00a0\u00a0\u00a0\u00a0\u00a0\u00a0\u00a0\u00a0App\\Controllers\\Home->reports()","index":"\u00a0\u00a04\u00a0\u00a0\u00a0\u00a0"},{"file":"SYSTEMPATH\\CodeIgniter.php:497","function":"\u00a0\u00a0\u00a0\u00a0\u00a0\u00a0\u00a0\u00a0CodeIgniter\\CodeIgniter->runController()","index":"\u00a0\u00a05\u00a0\u00a0\u00a0\u00a0"},{"file":"SYSTEMPATH\\CodeIgniter.php:366","function":"\u00a0\u00a0\u00a0\u00a0\u00a0\u00a0\u00a0\u00a0CodeIgniter\\CodeIgniter->handleRequest()","index":"\u00a0\u00a06\u00a0\u00a0\u00a0\u00a0"},{"file":"FCPATH\\index.php:68","function":"\u00a0\u00a0\u00a0\u00a0\u00a0\u00a0\u00a0\u00a0CodeIgniter\\CodeIgniter->run()","index":"\u00a0\u00a07\u00a0\u00a0\u00a0\u00a0"}],"trace-file":"APPPATH\\Models\\BillModel.php:60","qid":"7954692c9f433220720503b30f489e4b"},{"hover":"","class":"","duration":"0.16 ms","sql":"<strong>SELECT<\/strong> <strong>COUNT<\/strong>(`trans_id`) <strong>AS<\/strong> `trans_id`\n<strong>FROM<\/strong> `trans`\n<strong>WHERE<\/strong> `trans_type` = &#039;Thu&#039;\n<strong>AND<\/strong> `status` = 1\n<strong>AND<\/strong> `trans_date` &gt;= &#039;2023-10-19 00:00:00&#039;\n<strong>AND<\/strong> `trans_date` &lt;= &#039;2023-10-19 15:30:45&#039;","trace":[{"file":"SYSTEMPATH\\Database\\BaseBuilder.php:1616","function":"\u00a0\u00a0\u00a0\u00a0\u00a0\u00a0\u00a0\u00a0CodeIgniter\\Database\\BaseConnection->query()","index":"\u00a0\u00a01\u00a0\u00a0\u00a0\u00a0"},{"file":"APPPATH\\Models\\TransModel.php:126","function":"\u00a0\u00a0\u00a0\u00a0\u00a0\u00a0\u00a0\u00a0CodeIgniter\\Database\\BaseBuilder->get()","index":"\u00a0\u00a02\u00a0\u00a0\u00a0\u00a0"},{"file":"APPPATH\\Controllers\\Home.php:2251","function":"\u00a0\u00a0\u00a0\u00a0\u00a0\u00a0\u00a0\u00a0App\\Models\\TransModel->isAlreadyExist()","index":"\u00a0\u00a03\u00a0\u00a0\u00a0\u00a0"},{"file":"SYSTEMPATH\\CodeIgniter.php:932","function":"\u00a0\u00a0\u00a0\u00a0\u00a0\u00a0\u00a0\u00a0App\\Controllers\\Home->reports()","index":"\u00a0\u00a04\u00a0\u00a0\u00a0\u00a0"},{"file":"SYSTEMPATH\\CodeIgniter.php:497","function":"\u00a0\u00a0\u00a0\u00a0\u00a0\u00a0\u00a0\u00a0CodeIgniter\\CodeIgniter->runController()","index":"\u00a0\u00a05\u00a0\u00a0\u00a0\u00a0"},{"file":"SYSTEMPATH\\CodeIgniter.php:366","function":"\u00a0\u00a0\u00a0\u00a0\u00a0\u00a0\u00a0\u00a0CodeIgniter\\CodeIgniter->handleRequest()","index":"\u00a0\u00a06\u00a0\u00a0\u00a0\u00a0"},{"file":"FCPATH\\index.php:68","function":"\u00a0\u00a0\u00a0\u00a0\u00a0\u00a0\u00a0\u00a0CodeIgniter\\CodeIgniter->run()","index":"\u00a0\u00a07\u00a0\u00a0\u00a0\u00a0"}],"trace-file":"APPPATH\\Models\\TransModel.php:126","qid":"d32737f15d07d96d7ddd3163cf0a0cf7"},{"hover":"","class":"","duration":"0.16 ms","sql":"<strong>SELECT<\/strong> <strong>SUM<\/strong>(money) as money\n<strong>FROM<\/strong> `trans`\n<strong>WHERE<\/strong> `trans_type` = &#039;Thu&#039;\n<strong>AND<\/strong> `status` = 1\n<strong>AND<\/strong> `trans_date` &gt;= &#039;2023-10-19 00:00:00&#039;\n<strong>AND<\/strong> `trans_date` &lt;= &#039;2023-10-19 15:30:45&#039;","trace":[{"file":"SYSTEMPATH\\Database\\BaseBuilder.php:1616","function":"\u00a0\u00a0\u00a0\u00a0\u00a0\u00a0\u00a0\u00a0CodeIgniter\\Database\\BaseConnection->query()","index":"\u00a0\u00a01\u00a0\u00a0\u00a0\u00a0"},{"file":"APPPATH\\Models\\TransModel.php:94","function":"\u00a0\u00a0\u00a0\u00a0\u00a0\u00a0\u00a0\u00a0CodeIgniter\\Database\\BaseBuilder->get()","index":"\u00a0\u00a02\u00a0\u00a0\u00a0\u00a0"},{"file":"APPPATH\\Controllers\\Home.php:2251","function":"\u00a0\u00a0\u00a0\u00a0\u00a0\u00a0\u00a0\u00a0App\\Models\\TransModel->sumOptions()","index":"\u00a0\u00a03\u00a0\u00a0\u00a0\u00a0"},{"file":"SYSTEMPATH\\CodeIgniter.php:932","function":"\u00a0\u00a0\u00a0\u00a0\u00a0\u00a0\u00a0\u00a0App\\Controllers\\Home->reports()","index":"\u00a0\u00a04\u00a0\u00a0\u00a0\u00a0"},{"file":"SYSTEMPATH\\CodeIgniter.php:497","function":"\u00a0\u00a0\u00a0\u00a0\u00a0\u00a0\u00a0\u00a0CodeIgniter\\CodeIgniter->runController()","index":"\u00a0\u00a05\u00a0\u00a0\u00a0\u00a0"},{"file":"SYSTEMPATH\\CodeIgniter.php:366","function":"\u00a0\u00a0\u00a0\u00a0\u00a0\u00a0\u00a0\u00a0CodeIgniter\\CodeIgniter->handleRequest()","index":"\u00a0\u00a06\u00a0\u00a0\u00a0\u00a0"},{"file":"FCPATH\\index.php:68","function":"\u00a0\u00a0\u00a0\u00a0\u00a0\u00a0\u00a0\u00a0CodeIgniter\\CodeIgniter->run()","index":"\u00a0\u00a07\u00a0\u00a0\u00a0\u00a0"}],"trace-file":"APPPATH\\Models\\TransModel.php:94","qid":"2cc01a2c3779a0d7156104d5c4fefc7c"},{"hover":"","class":"","duration":"0.21 ms","sql":"<strong>SELECT<\/strong> <strong>COUNT<\/strong>(`trans_id`) <strong>AS<\/strong> `trans_id`\n<strong>FROM<\/strong> `trans`\n<strong>WHERE<\/strong> `trans_type` = &#039;Chi&#039;\n<strong>AND<\/strong> `status` = 1\n<strong>AND<\/strong> `trans_date` &gt;= &#039;2023-10-19 00:00:00&#039;\n<strong>AND<\/strong> `trans_date` &lt;= &#039;2023-10-19 15:30:45&#039;","trace":[{"file":"SYSTEMPATH\\Database\\BaseBuilder.php:1616","function":"\u00a0\u00a0\u00a0\u00a0\u00a0\u00a0\u00a0\u00a0CodeIgniter\\Database\\BaseConnection->query()","index":"\u00a0\u00a01\u00a0\u00a0\u00a0\u00a0"},{"file":"APPPATH\\Models\\TransModel.php:126","function":"\u00a0\u00a0\u00a0\u00a0\u00a0\u00a0\u00a0\u00a0CodeIgniter\\Database\\BaseBuilder->get()","index":"\u00a0\u00a02\u00a0\u00a0\u00a0\u00a0"},{"file":"APPPATH\\Controllers\\Home.php:2255","function":"\u00a0\u00a0\u00a0\u00a0\u00a0\u00a0\u00a0\u00a0App\\Models\\TransModel->isAlreadyExist()","index":"\u00a0\u00a03\u00a0\u00a0\u00a0\u00a0"},{"file":"SYSTEMPATH\\CodeIgniter.php:932","function":"\u00a0\u00a0\u00a0\u00a0\u00a0\u00a0\u00a0\u00a0App\\Controllers\\Home->reports()","index":"\u00a0\u00a04\u00a0\u00a0\u00a0\u00a0"},{"file":"SYSTEMPATH\\CodeIgniter.php:497","function":"\u00a0\u00a0\u00a0\u00a0\u00a0\u00a0\u00a0\u00a0CodeIgniter\\CodeIgniter->runController()","index":"\u00a0\u00a05\u00a0\u00a0\u00a0\u00a0"},{"file":"SYSTEMPATH\\CodeIgniter.php:366","function":"\u00a0\u00a0\u00a0\u00a0\u00a0\u00a0\u00a0\u00a0CodeIgniter\\CodeIgniter->handleRequest()","index":"\u00a0\u00a06\u00a0\u00a0\u00a0\u00a0"},{"file":"FCPATH\\index.php:68","function":"\u00a0\u00a0\u00a0\u00a0\u00a0\u00a0\u00a0\u00a0CodeIgniter\\CodeIgniter->run()","index":"\u00a0\u00a07\u00a0\u00a0\u00a0\u00a0"}],"trace-file":"APPPATH\\Models\\TransModel.php:126","qid":"957267f1b25c274591f1f02372b09747"},{"hover":"","class":"","duration":"0.19 ms","sql":"<strong>SELECT<\/strong> <strong>SUM<\/strong>(money) as money\n<strong>FROM<\/strong> `trans`\n<strong>WHERE<\/strong> `trans_type` = &#039;Chi&#039;\n<strong>AND<\/strong> `status` = 1\n<strong>AND<\/strong> `trans_date` &gt;= &#039;2023-10-19 00:00:00&#039;\n<strong>AND<\/strong> `trans_date` &lt;= &#039;2023-10-19 15:30:45&#039;","trace":[{"file":"SYSTEMPATH\\Database\\BaseBuilder.php:1616","function":"\u00a0\u00a0\u00a0\u00a0\u00a0\u00a0\u00a0\u00a0CodeIgniter\\Database\\BaseConnection->query()","index":"\u00a0\u00a01\u00a0\u00a0\u00a0\u00a0"},{"file":"APPPATH\\Models\\TransModel.php:94","function":"\u00a0\u00a0\u00a0\u00a0\u00a0\u00a0\u00a0\u00a0CodeIgniter\\Database\\BaseBuilder->get()","index":"\u00a0\u00a02\u00a0\u00a0\u00a0\u00a0"},{"file":"APPPATH\\Controllers\\Home.php:2255","function":"\u00a0\u00a0\u00a0\u00a0\u00a0\u00a0\u00a0\u00a0App\\Models\\TransModel->sumOptions()","index":"\u00a0\u00a03\u00a0\u00a0\u00a0\u00a0"},{"file":"SYSTEMPATH\\CodeIgniter.php:932","function":"\u00a0\u00a0\u00a0\u00a0\u00a0\u00a0\u00a0\u00a0App\\Controllers\\Home->reports()","index":"\u00a0\u00a04\u00a0\u00a0\u00a0\u00a0"},{"file":"SYSTEMPATH\\CodeIgniter.php:497","function":"\u00a0\u00a0\u00a0\u00a0\u00a0\u00a0\u00a0\u00a0CodeIgniter\\CodeIgniter->runController()","index":"\u00a0\u00a05\u00a0\u00a0\u00a0\u00a0"},{"file":"SYSTEMPATH\\CodeIgniter.php:366","function":"\u00a0\u00a0\u00a0\u00a0\u00a0\u00a0\u00a0\u00a0CodeIgniter\\CodeIgniter->handleRequest()","index":"\u00a0\u00a06\u00a0\u00a0\u00a0\u00a0"},{"file":"FCPATH\\index.php:68","function":"\u00a0\u00a0\u00a0\u00a0\u00a0\u00a0\u00a0\u00a0CodeIgniter\\CodeIgniter->run()","index":"\u00a0\u00a07\u00a0\u00a0\u00a0\u00a0"}],"trace-file":"APPPATH\\Models\\TransModel.php:94","qid":"53ec6121532e4e9379ab5b67d8bd20c4"},{"hover":"","class":"","duration":"0.22 ms","sql":"<strong>SELECT<\/strong> *\n<strong>FROM<\/strong> `bill_detail`\n<strong>WHERE<\/strong> `bill_id` = &#039;21&#039;","trace":[{"file":"SYSTEMPATH\\Database\\BaseBuilder.php:1616","function":"\u00a0\u00a0\u00a0\u00a0\u00a0\u00a0\u00a0\u00a0CodeIgniter\\Database\\BaseConnection->query()","index":"\u00a0\u00a01\u00a0\u00a0\u00a0\u00a0"},{"file":"APPPATH\\Models\\BillDetailModel.php:64","function":"\u00a0\u00a0\u00a0\u00a0\u00a0\u00a0\u00a0\u00a0CodeIgniter\\Database\\BaseBuilder->get()","index":"\u00a0\u00a02\u00a0\u00a0\u00a0\u00a0"},{"file":"APPPATH\\Controllers\\Home.php:2358","function":"\u00a0\u00a0\u00a0\u00a0\u00a0\u00a0\u00a0\u00a0App\\Models\\BillDetailModel->readOptions()","index":"\u00a0\u00a03\u00a0\u00a0\u00a0\u00a0"},{"file":"SYSTEMPATH\\CodeIgniter.php:932","function":"\u00a0\u00a0\u00a0\u00a0\u00a0\u00a0\u00a0\u00a0App\\Controllers\\Home->reports()","index":"\u00a0\u00a04\u00a0\u00a0\u00a0\u00a0"},{"file":"SYSTEMPATH\\CodeIgniter.php:497","function":"\u00a0\u00a0\u00a0\u00a0\u00a0\u00a0\u00a0\u00a0CodeIgniter\\CodeIgniter->runController()","index":"\u00a0\u00a05\u00a0\u00a0\u00a0\u00a0"},{"file":"SYSTEMPATH\\CodeIgniter.php:366","function":"\u00a0\u00a0\u00a0\u00a0\u00a0\u00a0\u00a0\u00a0CodeIgniter\\CodeIgniter->handleRequest()","index":"\u00a0\u00a06\u00a0\u00a0\u00a0\u00a0"},{"file":"FCPATH\\index.php:68","function":"\u00a0\u00a0\u00a0\u00a0\u00a0\u00a0\u00a0\u00a0CodeIgniter\\CodeIgniter->run()","index":"\u00a0\u00a07\u00a0\u00a0\u00a0\u00a0"}],"trace-file":"APPPATH\\Models\\BillDetailModel.php:64","qid":"490af24af98ed4c5f3c2591ffdb9861a"},{"hover":"","class":"","duration":"0.16 ms","sql":"<strong>SELECT<\/strong> *\n<strong>FROM<\/strong> `bill_detail`\n<strong>WHERE<\/strong> `bill_id` = &#039;22&#039;","trace":[{"file":"SYSTEMPATH\\Database\\BaseBuilder.php:1616","function":"\u00a0\u00a0\u00a0\u00a0\u00a0\u00a0\u00a0\u00a0CodeIgniter\\Database\\BaseConnection->query()","index":"\u00a0\u00a01\u00a0\u00a0\u00a0\u00a0"},{"file":"APPPATH\\Models\\BillDetailModel.php:64","function":"\u00a0\u00a0\u00a0\u00a0\u00a0\u00a0\u00a0\u00a0CodeIgniter\\Database\\BaseBuilder->get()","index":"\u00a0\u00a02\u00a0\u00a0\u00a0\u00a0"},{"file":"APPPATH\\Controllers\\Home.php:2358","function":"\u00a0\u00a0\u00a0\u00a0\u00a0\u00a0\u00a0\u00a0App\\Models\\BillDetailModel->readOptions()","index":"\u00a0\u00a03\u00a0\u00a0\u00a0\u00a0"},{"file":"SYSTEMPATH\\CodeIgniter.php:932","function":"\u00a0\u00a0\u00a0\u00a0\u00a0\u00a0\u00a0\u00a0App\\Controllers\\Home->reports()","index":"\u00a0\u00a04\u00a0\u00a0\u00a0\u00a0"},{"file":"SYSTEMPATH\\CodeIgniter.php:497","function":"\u00a0\u00a0\u00a0\u00a0\u00a0\u00a0\u00a0\u00a0CodeIgniter\\CodeIgniter->runController()","index":"\u00a0\u00a05\u00a0\u00a0\u00a0\u00a0"},{"file":"SYSTEMPATH\\CodeIgniter.php:366","function":"\u00a0\u00a0\u00a0\u00a0\u00a0\u00a0\u00a0\u00a0CodeIgniter\\CodeIgniter->handleRequest()","index":"\u00a0\u00a06\u00a0\u00a0\u00a0\u00a0"},{"file":"FCPATH\\index.php:68","function":"\u00a0\u00a0\u00a0\u00a0\u00a0\u00a0\u00a0\u00a0CodeIgniter\\CodeIgniter->run()","index":"\u00a0\u00a07\u00a0\u00a0\u00a0\u00a0"}],"trace-file":"APPPATH\\Models\\BillDetailModel.php:64","qid":"900f0fbfba476aae61b1c1d371c3b7a6"},{"hover":"","class":"","duration":"0.14 ms","sql":"<strong>SELECT<\/strong> *\n<strong>FROM<\/strong> `bill_detail`\n<strong>WHERE<\/strong> `bill_id` = &#039;23&#039;","trace":[{"file":"SYSTEMPATH\\Database\\BaseBuilder.php:1616","function":"\u00a0\u00a0\u00a0\u00a0\u00a0\u00a0\u00a0\u00a0CodeIgniter\\Database\\BaseConnection->query()","index":"\u00a0\u00a01\u00a0\u00a0\u00a0\u00a0"},{"file":"APPPATH\\Models\\BillDetailModel.php:64","function":"\u00a0\u00a0\u00a0\u00a0\u00a0\u00a0\u00a0\u00a0CodeIgniter\\Database\\BaseBuilder->get()","index":"\u00a0\u00a02\u00a0\u00a0\u00a0\u00a0"},{"file":"APPPATH\\Controllers\\Home.php:2358","function":"\u00a0\u00a0\u00a0\u00a0\u00a0\u00a0\u00a0\u00a0App\\Models\\BillDetailModel->readOptions()","index":"\u00a0\u00a03\u00a0\u00a0\u00a0\u00a0"},{"file":"SYSTEMPATH\\CodeIgniter.php:932","function":"\u00a0\u00a0\u00a0\u00a0\u00a0\u00a0\u00a0\u00a0App\\Controllers\\Home->reports()","index":"\u00a0\u00a04\u00a0\u00a0\u00a0\u00a0"},{"file":"SYSTEMPATH\\CodeIgniter.php:497","function":"\u00a0\u00a0\u00a0\u00a0\u00a0\u00a0\u00a0\u00a0CodeIgniter\\CodeIgniter->runController()","index":"\u00a0\u00a05\u00a0\u00a0\u00a0\u00a0"},{"file":"SYSTEMPATH\\CodeIgniter.php:366","function":"\u00a0\u00a0\u00a0\u00a0\u00a0\u00a0\u00a0\u00a0CodeIgniter\\CodeIgniter->handleRequest()","index":"\u00a0\u00a06\u00a0\u00a0\u00a0\u00a0"},{"file":"FCPATH\\index.php:68","function":"\u00a0\u00a0\u00a0\u00a0\u00a0\u00a0\u00a0\u00a0CodeIgniter\\CodeIgniter->run()","index":"\u00a0\u00a07\u00a0\u00a0\u00a0\u00a0"}],"trace-file":"APPPATH\\Models\\BillDetailModel.php:64","qid":"c0811ce7a47eb942a9707e8dd8071602"},{"hover":"","class":"","duration":"0.13 ms","sql":"<strong>SELECT<\/strong> *\n<strong>FROM<\/strong> `bill_detail`\n<strong>WHERE<\/strong> `bill_id` = &#039;24&#039;","trace":[{"file":"SYSTEMPATH\\Database\\BaseBuilder.php:1616","function":"\u00a0\u00a0\u00a0\u00a0\u00a0\u00a0\u00a0\u00a0CodeIgniter\\Database\\BaseConnection->query()","index":"\u00a0\u00a01\u00a0\u00a0\u00a0\u00a0"},{"file":"APPPATH\\Models\\BillDetailModel.php:64","function":"\u00a0\u00a0\u00a0\u00a0\u00a0\u00a0\u00a0\u00a0CodeIgniter\\Database\\BaseBuilder->get()","index":"\u00a0\u00a02\u00a0\u00a0\u00a0\u00a0"},{"file":"APPPATH\\Controllers\\Home.php:2358","function":"\u00a0\u00a0\u00a0\u00a0\u00a0\u00a0\u00a0\u00a0App\\Models\\BillDetailModel->readOptions()","index":"\u00a0\u00a03\u00a0\u00a0\u00a0\u00a0"},{"file":"SYSTEMPATH\\CodeIgniter.php:932","function":"\u00a0\u00a0\u00a0\u00a0\u00a0\u00a0\u00a0\u00a0App\\Controllers\\Home->reports()","index":"\u00a0\u00a04\u00a0\u00a0\u00a0\u00a0"},{"file":"SYSTEMPATH\\CodeIgniter.php:497","function":"\u00a0\u00a0\u00a0\u00a0\u00a0\u00a0\u00a0\u00a0CodeIgniter\\CodeIgniter->runController()","index":"\u00a0\u00a05\u00a0\u00a0\u00a0\u00a0"},{"file":"SYSTEMPATH\\CodeIgniter.php:366","function":"\u00a0\u00a0\u00a0\u00a0\u00a0\u00a0\u00a0\u00a0CodeIgniter\\CodeIgniter->handleRequest()","index":"\u00a0\u00a06\u00a0\u00a0\u00a0\u00a0"},{"file":"FCPATH\\index.php:68","function":"\u00a0\u00a0\u00a0\u00a0\u00a0\u00a0\u00a0\u00a0CodeIgniter\\CodeIgniter->run()","index":"\u00a0\u00a07\u00a0\u00a0\u00a0\u00a0"}],"trace-file":"APPPATH\\Models\\BillDetailModel.php:64","qid":"e81a443101621a28a5ffc52dbb589288"},{"hover":"","class":"","duration":"0.16 ms","sql":"<strong>SELECT<\/strong> *\n<strong>FROM<\/strong> `bill_detail`\n<strong>WHERE<\/strong> `bill_id` = &#039;25&#039;","trace":[{"file":"SYSTEMPATH\\Database\\BaseBuilder.php:1616","function":"\u00a0\u00a0\u00a0\u00a0\u00a0\u00a0\u00a0\u00a0CodeIgniter\\Database\\BaseConnection->query()","index":"\u00a0\u00a01\u00a0\u00a0\u00a0\u00a0"},{"file":"APPPATH\\Models\\BillDetailModel.php:64","function":"\u00a0\u00a0\u00a0\u00a0\u00a0\u00a0\u00a0\u00a0CodeIgniter\\Database\\BaseBuilder->get()","index":"\u00a0\u00a02\u00a0\u00a0\u00a0\u00a0"},{"file":"APPPATH\\Controllers\\Home.php:2358","function":"\u00a0\u00a0\u00a0\u00a0\u00a0\u00a0\u00a0\u00a0App\\Models\\BillDetailModel->readOptions()","index":"\u00a0\u00a03\u00a0\u00a0\u00a0\u00a0"},{"file":"SYSTEMPATH\\CodeIgniter.php:932","function":"\u00a0\u00a0\u00a0\u00a0\u00a0\u00a0\u00a0\u00a0App\\Controllers\\Home->reports()","index":"\u00a0\u00a04\u00a0\u00a0\u00a0\u00a0"},{"file":"SYSTEMPATH\\CodeIgniter.php:497","function":"\u00a0\u00a0\u00a0\u00a0\u00a0\u00a0\u00a0\u00a0CodeIgniter\\CodeIgniter->runController()","index":"\u00a0\u00a05\u00a0\u00a0\u00a0\u00a0"},{"file":"SYSTEMPATH\\CodeIgniter.php:366","function":"\u00a0\u00a0\u00a0\u00a0\u00a0\u00a0\u00a0\u00a0CodeIgniter\\CodeIgniter->handleRequest()","index":"\u00a0\u00a06\u00a0\u00a0\u00a0\u00a0"},{"file":"FCPATH\\index.php:68","function":"\u00a0\u00a0\u00a0\u00a0\u00a0\u00a0\u00a0\u00a0CodeIgniter\\CodeIgniter->run()","index":"\u00a0\u00a07\u00a0\u00a0\u00a0\u00a0"}],"trace-file":"APPPATH\\Models\\BillDetailModel.php:64","qid":"0a42d81a83519a4dd2cfe09cacf2aa3a"},{"hover":"","class":"","duration":"0.15 ms","sql":"<strong>SELECT<\/strong> *\n<strong>FROM<\/strong> `bill_detail`\n<strong>WHERE<\/strong> `bill_id` = &#039;27&#039;","trace":[{"file":"SYSTEMPATH\\Database\\BaseBuilder.php:1616","function":"\u00a0\u00a0\u00a0\u00a0\u00a0\u00a0\u00a0\u00a0CodeIgniter\\Database\\BaseConnection->query()","index":"\u00a0\u00a01\u00a0\u00a0\u00a0\u00a0"},{"file":"APPPATH\\Models\\BillDetailModel.php:64","function":"\u00a0\u00a0\u00a0\u00a0\u00a0\u00a0\u00a0\u00a0CodeIgniter\\Database\\BaseBuilder->get()","index":"\u00a0\u00a02\u00a0\u00a0\u00a0\u00a0"},{"file":"APPPATH\\Controllers\\Home.php:2358","function":"\u00a0\u00a0\u00a0\u00a0\u00a0\u00a0\u00a0\u00a0App\\Models\\BillDetailModel->readOptions()","index":"\u00a0\u00a03\u00a0\u00a0\u00a0\u00a0"},{"file":"SYSTEMPATH\\CodeIgniter.php:932","function":"\u00a0\u00a0\u00a0\u00a0\u00a0\u00a0\u00a0\u00a0App\\Controllers\\Home->reports()","index":"\u00a0\u00a04\u00a0\u00a0\u00a0\u00a0"},{"file":"SYSTEMPATH\\CodeIgniter.php:497","function":"\u00a0\u00a0\u00a0\u00a0\u00a0\u00a0\u00a0\u00a0CodeIgniter\\CodeIgniter->runController()","index":"\u00a0\u00a05\u00a0\u00a0\u00a0\u00a0"},{"file":"SYSTEMPATH\\CodeIgniter.php:366","function":"\u00a0\u00a0\u00a0\u00a0\u00a0\u00a0\u00a0\u00a0CodeIgniter\\CodeIgniter->handleRequest()","index":"\u00a0\u00a06\u00a0\u00a0\u00a0\u00a0"},{"file":"FCPATH\\index.php:68","function":"\u00a0\u00a0\u00a0\u00a0\u00a0\u00a0\u00a0\u00a0CodeIgniter\\CodeIgniter->run()","index":"\u00a0\u00a07\u00a0\u00a0\u00a0\u00a0"}],"trace-file":"APPPATH\\Models\\BillDetailModel.php:64","qid":"c6f051bb5d89b24ff3049b021ceb77a7"},{"hover":"","class":"","duration":"0.17 ms","sql":"<strong>SELECT<\/strong> `food_id`, `food_name`, `description`, `status`, `catalog_id`\n<strong>FROM<\/strong> `food`","trace":[{"file":"SYSTEMPATH\\Database\\BaseBuilder.php:1616","function":"\u00a0\u00a0\u00a0\u00a0\u00a0\u00a0\u00a0\u00a0CodeIgniter\\Database\\BaseConnection->query()","index":"\u00a0\u00a01\u00a0\u00a0\u00a0\u00a0"},{"file":"APPPATH\\Models\\FoodModel.php:73","function":"\u00a0\u00a0\u00a0\u00a0\u00a0\u00a0\u00a0\u00a0CodeIgniter\\Database\\BaseBuilder->get()","index":"\u00a0\u00a02\u00a0\u00a0\u00a0\u00a0"},{"file":"APPPATH\\Controllers\\Home.php:2366","function":"\u00a0\u00a0\u00a0\u00a0\u00a0\u00a0\u00a0\u00a0App\\Models\\FoodModel->readAll()","index":"\u00a0\u00a03\u00a0\u00a0\u00a0\u00a0"},{"file":"SYSTEMPATH\\CodeIgniter.php:932","function":"\u00a0\u00a0\u00a0\u00a0\u00a0\u00a0\u00a0\u00a0App\\Controllers\\Home->reports()","index":"\u00a0\u00a04\u00a0\u00a0\u00a0\u00a0"},{"file":"SYSTEMPATH\\CodeIgniter.php:497","function":"\u00a0\u00a0\u00a0\u00a0\u00a0\u00a0\u00a0\u00a0CodeIgniter\\CodeIgniter->runController()","index":"\u00a0\u00a05\u00a0\u00a0\u00a0\u00a0"},{"file":"SYSTEMPATH\\CodeIgniter.php:366","function":"\u00a0\u00a0\u00a0\u00a0\u00a0\u00a0\u00a0\u00a0CodeIgniter\\CodeIgniter->handleRequest()","index":"\u00a0\u00a06\u00a0\u00a0\u00a0\u00a0"},{"file":"FCPATH\\index.php:68","function":"\u00a0\u00a0\u00a0\u00a0\u00a0\u00a0\u00a0\u00a0CodeIgniter\\CodeIgniter->run()","index":"\u00a0\u00a07\u00a0\u00a0\u00a0\u00a0"}],"trace-file":"APPPATH\\Models\\FoodModel.php:73","qid":"a447f046b83dc1c131c7664a53814444"},{"hover":"","class":"","duration":"0.15 ms","sql":"<strong>SELECT<\/strong> <strong>COUNT<\/strong>(`bill_detail_id`) <strong>AS<\/strong> `bill_detail_id`\n<strong>FROM<\/strong> `bill_detail`\n<strong>WHERE<\/strong> `food_id` = &#039;1&#039;\n<strong>AND<\/strong> `bill_id` <strong>IN<\/strong> (&#039;21&#039;,&#039;22&#039;,&#039;23&#039;,&#039;24&#039;,&#039;25&#039;,&#039;27&#039;)","trace":[{"file":"SYSTEMPATH\\Database\\BaseBuilder.php:1616","function":"\u00a0\u00a0\u00a0\u00a0\u00a0\u00a0\u00a0\u00a0CodeIgniter\\Database\\BaseConnection->query()","index":"\u00a0\u00a01\u00a0\u00a0\u00a0\u00a0"},{"file":"APPPATH\\Models\\BillDetailModel.php:135","function":"\u00a0\u00a0\u00a0\u00a0\u00a0\u00a0\u00a0\u00a0CodeIgniter\\Database\\BaseBuilder->get()","index":"\u00a0\u00a02\u00a0\u00a0\u00a0\u00a0"},{"file":"APPPATH\\Controllers\\Home.php:2373","function":"\u00a0\u00a0\u00a0\u00a0\u00a0\u00a0\u00a0\u00a0App\\Models\\BillDetailModel->isAlreadyExist2()","index":"\u00a0\u00a03\u00a0\u00a0\u00a0\u00a0"},{"file":"SYSTEMPATH\\CodeIgniter.php:932","function":"\u00a0\u00a0\u00a0\u00a0\u00a0\u00a0\u00a0\u00a0App\\Controllers\\Home->reports()","index":"\u00a0\u00a04\u00a0\u00a0\u00a0\u00a0"},{"file":"SYSTEMPATH\\CodeIgniter.php:497","function":"\u00a0\u00a0\u00a0\u00a0\u00a0\u00a0\u00a0\u00a0CodeIgniter\\CodeIgniter->runController()","index":"\u00a0\u00a05\u00a0\u00a0\u00a0\u00a0"},{"file":"SYSTEMPATH\\CodeIgniter.php:366","function":"\u00a0\u00a0\u00a0\u00a0\u00a0\u00a0\u00a0\u00a0CodeIgniter\\CodeIgniter->handleRequest()","index":"\u00a0\u00a06\u00a0\u00a0\u00a0\u00a0"},{"file":"FCPATH\\index.php:68","function":"\u00a0\u00a0\u00a0\u00a0\u00a0\u00a0\u00a0\u00a0CodeIgniter\\CodeIgniter->run()","index":"\u00a0\u00a07\u00a0\u00a0\u00a0\u00a0"}],"trace-file":"APPPATH\\Models\\BillDetailModel.php:135","qid":"489df982fcff91fa7cb217cd17135384"},{"hover":"","class":"","duration":"0.15 ms","sql":"<strong>SELECT<\/strong> <strong>SUM<\/strong>(count) as count\n<strong>FROM<\/strong> `bill_detail`\n<strong>WHERE<\/strong> `food_id` = &#039;1&#039;\n<strong>AND<\/strong> `bill_id` <strong>IN<\/strong> (&#039;21&#039;,&#039;22&#039;,&#039;23&#039;,&#039;24&#039;,&#039;25&#039;,&#039;27&#039;)","trace":[{"file":"SYSTEMPATH\\Database\\BaseBuilder.php:1616","function":"\u00a0\u00a0\u00a0\u00a0\u00a0\u00a0\u00a0\u00a0CodeIgniter\\Database\\BaseConnection->query()","index":"\u00a0\u00a01\u00a0\u00a0\u00a0\u00a0"},{"file":"APPPATH\\Models\\BillDetailModel.php:94","function":"\u00a0\u00a0\u00a0\u00a0\u00a0\u00a0\u00a0\u00a0CodeIgniter\\Database\\BaseBuilder->get()","index":"\u00a0\u00a02\u00a0\u00a0\u00a0\u00a0"},{"file":"APPPATH\\Controllers\\Home.php:2373","function":"\u00a0\u00a0\u00a0\u00a0\u00a0\u00a0\u00a0\u00a0App\\Models\\BillDetailModel->sumOptions2()","index":"\u00a0\u00a03\u00a0\u00a0\u00a0\u00a0"},{"file":"SYSTEMPATH\\CodeIgniter.php:932","function":"\u00a0\u00a0\u00a0\u00a0\u00a0\u00a0\u00a0\u00a0App\\Controllers\\Home->reports()","index":"\u00a0\u00a04\u00a0\u00a0\u00a0\u00a0"},{"file":"SYSTEMPATH\\CodeIgniter.php:497","function":"\u00a0\u00a0\u00a0\u00a0\u00a0\u00a0\u00a0\u00a0CodeIgniter\\CodeIgniter->runController()","index":"\u00a0\u00a05\u00a0\u00a0\u00a0\u00a0"},{"file":"SYSTEMPATH\\CodeIgniter.php:366","function":"\u00a0\u00a0\u00a0\u00a0\u00a0\u00a0\u00a0\u00a0CodeIgniter\\CodeIgniter->handleRequest()","index":"\u00a0\u00a06\u00a0\u00a0\u00a0\u00a0"},{"file":"FCPATH\\index.php:68","function":"\u00a0\u00a0\u00a0\u00a0\u00a0\u00a0\u00a0\u00a0CodeIgniter\\CodeIgniter->run()","index":"\u00a0\u00a07\u00a0\u00a0\u00a0\u00a0"}],"trace-file":"APPPATH\\Models\\BillDetailModel.php:94","qid":"3931fd1f0ff66f5219a95b72fb5a1b7f"},{"hover":"","class":"","duration":"0.12 ms","sql":"<strong>SELECT<\/strong> <strong>COUNT<\/strong>(`bill_detail_id`) <strong>AS<\/strong> `bill_detail_id`\n<strong>FROM<\/strong> `bill_detail`\n<strong>WHERE<\/strong> `food_id` = &#039;2&#039;\n<strong>AND<\/strong> `bill_id` <strong>IN<\/strong> (&#039;21&#039;,&#039;22&#039;,&#039;23&#039;,&#039;24&#039;,&#039;25&#039;,&#039;27&#039;)","trace":[{"file":"SYSTEMPATH\\Database\\BaseBuilder.php:1616","function":"\u00a0\u00a0\u00a0\u00a0\u00a0\u00a0\u00a0\u00a0CodeIgniter\\Database\\BaseConnection->query()","index":"\u00a0\u00a01\u00a0\u00a0\u00a0\u00a0"},{"file":"APPPATH\\Models\\BillDetailModel.php:135","function":"\u00a0\u00a0\u00a0\u00a0\u00a0\u00a0\u00a0\u00a0CodeIgniter\\Database\\BaseBuilder->get()","index":"\u00a0\u00a02\u00a0\u00a0\u00a0\u00a0"},{"file":"APPPATH\\Controllers\\Home.php:2373","function":"\u00a0\u00a0\u00a0\u00a0\u00a0\u00a0\u00a0\u00a0App\\Models\\BillDetailModel->isAlreadyExist2()","index":"\u00a0\u00a03\u00a0\u00a0\u00a0\u00a0"},{"file":"SYSTEMPATH\\CodeIgniter.php:932","function":"\u00a0\u00a0\u00a0\u00a0\u00a0\u00a0\u00a0\u00a0App\\Controllers\\Home->reports()","index":"\u00a0\u00a04\u00a0\u00a0\u00a0\u00a0"},{"file":"SYSTEMPATH\\CodeIgniter.php:497","function":"\u00a0\u00a0\u00a0\u00a0\u00a0\u00a0\u00a0\u00a0CodeIgniter\\CodeIgniter->runController()","index":"\u00a0\u00a05\u00a0\u00a0\u00a0\u00a0"},{"file":"SYSTEMPATH\\CodeIgniter.php:366","function":"\u00a0\u00a0\u00a0\u00a0\u00a0\u00a0\u00a0\u00a0CodeIgniter\\CodeIgniter->handleRequest()","index":"\u00a0\u00a06\u00a0\u00a0\u00a0\u00a0"},{"file":"FCPATH\\index.php:68","function":"\u00a0\u00a0\u00a0\u00a0\u00a0\u00a0\u00a0\u00a0CodeIgniter\\CodeIgniter->run()","index":"\u00a0\u00a07\u00a0\u00a0\u00a0\u00a0"}],"trace-file":"APPPATH\\Models\\BillDetailModel.php:135","qid":"9ae9cd46f0164be8f19f1fc79aebb1b9"},{"hover":"","class":"","duration":"0.12 ms","sql":"<strong>SELECT<\/strong> <strong>SUM<\/strong>(count) as count\n<strong>FROM<\/strong> `bill_detail`\n<strong>WHERE<\/strong> `food_id` = &#039;2&#039;\n<strong>AND<\/strong> `bill_id` <strong>IN<\/strong> (&#039;21&#039;,&#039;22&#039;,&#039;23&#039;,&#039;24&#039;,&#039;25&#039;,&#039;27&#039;)","trace":[{"file":"SYSTEMPATH\\Database\\BaseBuilder.php:1616","function":"\u00a0\u00a0\u00a0\u00a0\u00a0\u00a0\u00a0\u00a0CodeIgniter\\Database\\BaseConnection->query()","index":"\u00a0\u00a01\u00a0\u00a0\u00a0\u00a0"},{"file":"APPPATH\\Models\\BillDetailModel.php:94","function":"\u00a0\u00a0\u00a0\u00a0\u00a0\u00a0\u00a0\u00a0CodeIgniter\\Database\\BaseBuilder->get()","index":"\u00a0\u00a02\u00a0\u00a0\u00a0\u00a0"},{"file":"APPPATH\\Controllers\\Home.php:2373","function":"\u00a0\u00a0\u00a0\u00a0\u00a0\u00a0\u00a0\u00a0App\\Models\\BillDetailModel->sumOptions2()","index":"\u00a0\u00a03\u00a0\u00a0\u00a0\u00a0"},{"file":"SYSTEMPATH\\CodeIgniter.php:932","function":"\u00a0\u00a0\u00a0\u00a0\u00a0\u00a0\u00a0\u00a0App\\Controllers\\Home->reports()","index":"\u00a0\u00a04\u00a0\u00a0\u00a0\u00a0"},{"file":"SYSTEMPATH\\CodeIgniter.php:497","function":"\u00a0\u00a0\u00a0\u00a0\u00a0\u00a0\u00a0\u00a0CodeIgniter\\CodeIgniter->runController()","index":"\u00a0\u00a05\u00a0\u00a0\u00a0\u00a0"},{"file":"SYSTEMPATH\\CodeIgniter.php:366","function":"\u00a0\u00a0\u00a0\u00a0\u00a0\u00a0\u00a0\u00a0CodeIgniter\\CodeIgniter->handleRequest()","index":"\u00a0\u00a06\u00a0\u00a0\u00a0\u00a0"},{"file":"FCPATH\\index.php:68","function":"\u00a0\u00a0\u00a0\u00a0\u00a0\u00a0\u00a0\u00a0CodeIgniter\\CodeIgniter->run()","index":"\u00a0\u00a07\u00a0\u00a0\u00a0\u00a0"}],"trace-file":"APPPATH\\Models\\BillDetailModel.php:94","qid":"32d3b1ab2e6303220fc94ed12b51204c"},{"hover":"","class":"","duration":"0.12 ms","sql":"<strong>SELECT<\/strong> <strong>COUNT<\/strong>(`bill_detail_id`) <strong>AS<\/strong> `bill_detail_id`\n<strong>FROM<\/strong> `bill_detail`\n<strong>WHERE<\/strong> `food_id` = &#039;3&#039;\n<strong>AND<\/strong> `bill_id` <strong>IN<\/strong> (&#039;21&#039;,&#039;22&#039;,&#039;23&#039;,&#039;24&#039;,&#039;25&#039;,&#039;27&#039;)","trace":[{"file":"SYSTEMPATH\\Database\\BaseBuilder.php:1616","function":"\u00a0\u00a0\u00a0\u00a0\u00a0\u00a0\u00a0\u00a0CodeIgniter\\Database\\BaseConnection->query()","index":"\u00a0\u00a01\u00a0\u00a0\u00a0\u00a0"},{"file":"APPPATH\\Models\\BillDetailModel.php:135","function":"\u00a0\u00a0\u00a0\u00a0\u00a0\u00a0\u00a0\u00a0CodeIgniter\\Database\\BaseBuilder->get()","index":"\u00a0\u00a02\u00a0\u00a0\u00a0\u00a0"},{"file":"APPPATH\\Controllers\\Home.php:2373","function":"\u00a0\u00a0\u00a0\u00a0\u00a0\u00a0\u00a0\u00a0App\\Models\\BillDetailModel->isAlreadyExist2()","index":"\u00a0\u00a03\u00a0\u00a0\u00a0\u00a0"},{"file":"SYSTEMPATH\\CodeIgniter.php:932","function":"\u00a0\u00a0\u00a0\u00a0\u00a0\u00a0\u00a0\u00a0App\\Controllers\\Home->reports()","index":"\u00a0\u00a04\u00a0\u00a0\u00a0\u00a0"},{"file":"SYSTEMPATH\\CodeIgniter.php:497","function":"\u00a0\u00a0\u00a0\u00a0\u00a0\u00a0\u00a0\u00a0CodeIgniter\\CodeIgniter->runController()","index":"\u00a0\u00a05\u00a0\u00a0\u00a0\u00a0"},{"file":"SYSTEMPATH\\CodeIgniter.php:366","function":"\u00a0\u00a0\u00a0\u00a0\u00a0\u00a0\u00a0\u00a0CodeIgniter\\CodeIgniter->handleRequest()","index":"\u00a0\u00a06\u00a0\u00a0\u00a0\u00a0"},{"file":"FCPATH\\index.php:68","function":"\u00a0\u00a0\u00a0\u00a0\u00a0\u00a0\u00a0\u00a0CodeIgniter\\CodeIgniter->run()","index":"\u00a0\u00a07\u00a0\u00a0\u00a0\u00a0"}],"trace-file":"APPPATH\\Models\\BillDetailModel.php:135","qid":"a3fccdabb08a3d08d0a88b353e055090"},{"hover":"","class":"","duration":"0.12 ms","sql":"<strong>SELECT<\/strong> <strong>SUM<\/strong>(count) as count\n<strong>FROM<\/strong> `bill_detail`\n<strong>WHERE<\/strong> `food_id` = &#039;3&#039;\n<strong>AND<\/strong> `bill_id` <strong>IN<\/strong> (&#039;21&#039;,&#039;22&#039;,&#039;23&#039;,&#039;24&#039;,&#039;25&#039;,&#039;27&#039;)","trace":[{"file":"SYSTEMPATH\\Database\\BaseBuilder.php:1616","function":"\u00a0\u00a0\u00a0\u00a0\u00a0\u00a0\u00a0\u00a0CodeIgniter\\Database\\BaseConnection->query()","index":"\u00a0\u00a01\u00a0\u00a0\u00a0\u00a0"},{"file":"APPPATH\\Models\\BillDetailModel.php:94","function":"\u00a0\u00a0\u00a0\u00a0\u00a0\u00a0\u00a0\u00a0CodeIgniter\\Database\\BaseBuilder->get()","index":"\u00a0\u00a02\u00a0\u00a0\u00a0\u00a0"},{"file":"APPPATH\\Controllers\\Home.php:2373","function":"\u00a0\u00a0\u00a0\u00a0\u00a0\u00a0\u00a0\u00a0App\\Models\\BillDetailModel->sumOptions2()","index":"\u00a0\u00a03\u00a0\u00a0\u00a0\u00a0"},{"file":"SYSTEMPATH\\CodeIgniter.php:932","function":"\u00a0\u00a0\u00a0\u00a0\u00a0\u00a0\u00a0\u00a0App\\Controllers\\Home->reports()","index":"\u00a0\u00a04\u00a0\u00a0\u00a0\u00a0"},{"file":"SYSTEMPATH\\CodeIgniter.php:497","function":"\u00a0\u00a0\u00a0\u00a0\u00a0\u00a0\u00a0\u00a0CodeIgniter\\CodeIgniter->runController()","index":"\u00a0\u00a05\u00a0\u00a0\u00a0\u00a0"},{"file":"SYSTEMPATH\\CodeIgniter.php:366","function":"\u00a0\u00a0\u00a0\u00a0\u00a0\u00a0\u00a0\u00a0CodeIgniter\\CodeIgniter->handleRequest()","index":"\u00a0\u00a06\u00a0\u00a0\u00a0\u00a0"},{"file":"FCPATH\\index.php:68","function":"\u00a0\u00a0\u00a0\u00a0\u00a0\u00a0\u00a0\u00a0CodeIgniter\\CodeIgniter->run()","index":"\u00a0\u00a07\u00a0\u00a0\u00a0\u00a0"}],"trace-file":"APPPATH\\Models\\BillDetailModel.php:94","qid":"15c6262547655c47a482467aa649b535"},{"hover":"","class":"","duration":"0.13 ms","sql":"<strong>SELECT<\/strong> <strong>COUNT<\/strong>(`bill_detail_id`) <strong>AS<\/strong> `bill_detail_id`\n<strong>FROM<\/strong> `bill_detail`\n<strong>WHERE<\/strong> `food_id` = &#039;4&#039;\n<strong>AND<\/strong> `bill_id` <strong>IN<\/strong> (&#039;21&#039;,&#039;22&#039;,&#039;23&#039;,&#039;24&#039;,&#039;25&#039;,&#039;27&#039;)","trace":[{"file":"SYSTEMPATH\\Database\\BaseBuilder.php:1616","function":"\u00a0\u00a0\u00a0\u00a0\u00a0\u00a0\u00a0\u00a0CodeIgniter\\Database\\BaseConnection->query()","index":"\u00a0\u00a01\u00a0\u00a0\u00a0\u00a0"},{"file":"APPPATH\\Models\\BillDetailModel.php:135","function":"\u00a0\u00a0\u00a0\u00a0\u00a0\u00a0\u00a0\u00a0CodeIgniter\\Database\\BaseBuilder->get()","index":"\u00a0\u00a02\u00a0\u00a0\u00a0\u00a0"},{"file":"APPPATH\\Controllers\\Home.php:2373","function":"\u00a0\u00a0\u00a0\u00a0\u00a0\u00a0\u00a0\u00a0App\\Models\\BillDetailModel->isAlreadyExist2()","index":"\u00a0\u00a03\u00a0\u00a0\u00a0\u00a0"},{"file":"SYSTEMPATH\\CodeIgniter.php:932","function":"\u00a0\u00a0\u00a0\u00a0\u00a0\u00a0\u00a0\u00a0App\\Controllers\\Home->reports()","index":"\u00a0\u00a04\u00a0\u00a0\u00a0\u00a0"},{"file":"SYSTEMPATH\\CodeIgniter.php:497","function":"\u00a0\u00a0\u00a0\u00a0\u00a0\u00a0\u00a0\u00a0CodeIgniter\\CodeIgniter->runController()","index":"\u00a0\u00a05\u00a0\u00a0\u00a0\u00a0"},{"file":"SYSTEMPATH\\CodeIgniter.php:366","function":"\u00a0\u00a0\u00a0\u00a0\u00a0\u00a0\u00a0\u00a0CodeIgniter\\CodeIgniter->handleRequest()","index":"\u00a0\u00a06\u00a0\u00a0\u00a0\u00a0"},{"file":"FCPATH\\index.php:68","function":"\u00a0\u00a0\u00a0\u00a0\u00a0\u00a0\u00a0\u00a0CodeIgniter\\CodeIgniter->run()","index":"\u00a0\u00a07\u00a0\u00a0\u00a0\u00a0"}],"trace-file":"APPPATH\\Models\\BillDetailModel.php:135","qid":"00dbf2b1fb42f24b196351092bb6a328"},{"hover":"","class":"","duration":"0.12 ms","sql":"<strong>SELECT<\/strong> <strong>SUM<\/strong>(count) as count\n<strong>FROM<\/strong> `bill_detail`\n<strong>WHERE<\/strong> `food_id` = &#039;4&#039;\n<strong>AND<\/strong> `bill_id` <strong>IN<\/strong> (&#039;21&#039;,&#039;22&#039;,&#039;23&#039;,&#039;24&#039;,&#039;25&#039;,&#039;27&#039;)","trace":[{"file":"SYSTEMPATH\\Database\\BaseBuilder.php:1616","function":"\u00a0\u00a0\u00a0\u00a0\u00a0\u00a0\u00a0\u00a0CodeIgniter\\Database\\BaseConnection->query()","index":"\u00a0\u00a01\u00a0\u00a0\u00a0\u00a0"},{"file":"APPPATH\\Models\\BillDetailModel.php:94","function":"\u00a0\u00a0\u00a0\u00a0\u00a0\u00a0\u00a0\u00a0CodeIgniter\\Database\\BaseBuilder->get()","index":"\u00a0\u00a02\u00a0\u00a0\u00a0\u00a0"},{"file":"APPPATH\\Controllers\\Home.php:2373","function":"\u00a0\u00a0\u00a0\u00a0\u00a0\u00a0\u00a0\u00a0App\\Models\\BillDetailModel->sumOptions2()","index":"\u00a0\u00a03\u00a0\u00a0\u00a0\u00a0"},{"file":"SYSTEMPATH\\CodeIgniter.php:932","function":"\u00a0\u00a0\u00a0\u00a0\u00a0\u00a0\u00a0\u00a0App\\Controllers\\Home->reports()","index":"\u00a0\u00a04\u00a0\u00a0\u00a0\u00a0"},{"file":"SYSTEMPATH\\CodeIgniter.php:497","function":"\u00a0\u00a0\u00a0\u00a0\u00a0\u00a0\u00a0\u00a0CodeIgniter\\CodeIgniter->runController()","index":"\u00a0\u00a05\u00a0\u00a0\u00a0\u00a0"},{"file":"SYSTEMPATH\\CodeIgniter.php:366","function":"\u00a0\u00a0\u00a0\u00a0\u00a0\u00a0\u00a0\u00a0CodeIgniter\\CodeIgniter->handleRequest()","index":"\u00a0\u00a06\u00a0\u00a0\u00a0\u00a0"},{"file":"FCPATH\\index.php:68","function":"\u00a0\u00a0\u00a0\u00a0\u00a0\u00a0\u00a0\u00a0CodeIgniter\\CodeIgniter->run()","index":"\u00a0\u00a07\u00a0\u00a0\u00a0\u00a0"}],"trace-file":"APPPATH\\Models\\BillDetailModel.php:94","qid":"f3886c20e681b5861ecf82b5c9524d7e"}]},"badgeValue":24,"isEmpty":false,"hasTabContent":true,"hasLabel":false,"icon":"data:image\/png;base64,iVBORw0KGgoAAAANSUhEUgAAABgAAAAYCAYAAADgdz34AAAAAXNSR0IArs4c6QAAAARnQU1BAACxjwv8YQUAAAAJcEhZcwAADsMAAA7DAcdvqGQAAADMSURBVEhLY6A3YExLSwsA4nIycQDIDIhRWEBqamo\/UNF\/SjDQjF6ocZgAKPkRiFeEhoYyQ4WIBiA9QAuWAPEHqBAmgLqgHcolGQD1V4DMgHIxwbCxYD+QBqcKINseKo6eWrBioPrtQBq\/BcgY5ht0cUIYbBg2AJKkRxCNWkDQgtFUNJwtABr+F6igE8olGQD114HMgHIxAVDyAhA\/AlpSA8RYUwoeXAPVex5qHCbIyMgwBCkAuQJIY00huDBUz\/mUlBQDqHGjgBjAwAAACexpph6oHSQAAAAASUVORK5CYII=","hasTimelineData":true,"timelineData":[{"name":"Connecting to Database: \"default\"","component":"Database","start":1697704245.251723,"duration":"0.021582"},{"name":"Query","component":"Database","start":1697704245.274164,"duration":"0.000303","query":"<strong>SELECT<\/strong> <strong>COUNT<\/strong>(`bill_id`) <strong>AS<\/strong> `bill_id`\n<strong>FROM<\/strong> `bill`\n<strong>WHERE<\/strong> `status` = &#039;Done&#039;\n<strong>AND<\/strong> `date_check_out` &gt;= &#039;2023-10-19 00:00:00&#039;\n<strong>AND<\/strong> `date_check_out` &lt;= &#039;2023-10-19 15:30:45&#039;"},{"name":"Query","component":"Database","start":1697704245.275732,"duration":"0.000180","query":"<strong>SELECT<\/strong> *\n<strong>FROM<\/strong> `bill`\n<strong>WHERE<\/strong> `status` = &#039;Done&#039;\n<strong>AND<\/strong> `date_check_out` &gt;= &#039;2023-10-19 00:00:00&#039;\n<strong>AND<\/strong> `date_check_out` &lt;= &#039;2023-10-19 15:30:45&#039;"},{"name":"Query","component":"Database","start":1697704245.276015,"duration":"0.000141","query":"<strong>SELECT<\/strong> <strong>COUNT<\/strong>(bill_id) as bill_id\n<strong>FROM<\/strong> `bill`\n<strong>WHERE<\/strong> `status` = &#039;Done&#039;\n<strong>AND<\/strong> `date_check_out` &gt;= &#039;2023-10-19 00:00:00&#039;\n<strong>AND<\/strong> `date_check_out` &lt;= &#039;2023-10-19 15:30:45&#039;"},{"name":"Query","component":"Database","start":1697704245.276245,"duration":"0.000194","query":"<strong>SELECT<\/strong> <strong>SUM<\/strong>(sum_orders) as sum_orders\n<strong>FROM<\/strong> `bill`\n<strong>WHERE<\/strong> `status` = &#039;Done&#039;\n<strong>AND<\/strong> `date_check_out` &gt;= &#039;2023-10-19 00:00:00&#039;\n<strong>AND<\/strong> `date_check_out` &lt;= &#039;2023-10-19 15:30:45&#039;"},{"name":"Query","component":"Database","start":1697704245.276519,"duration":"0.000173","query":"<strong>SELECT<\/strong> <strong>SUM<\/strong>(total) as total\n<strong>FROM<\/strong> `bill`\n<strong>WHERE<\/strong> `status` = &#039;Done&#039;\n<strong>AND<\/strong> `date_check_out` &gt;= &#039;2023-10-19 00:00:00&#039;\n<strong>AND<\/strong> `date_check_out` &lt;= &#039;2023-10-19 15:30:45&#039;"},{"name":"Query","component":"Database","start":1697704245.276786,"duration":"0.000165","query":"<strong>SELECT<\/strong> <strong>COUNT<\/strong>(`trans_id`) <strong>AS<\/strong> `trans_id`\n<strong>FROM<\/strong> `trans`\n<strong>WHERE<\/strong> `trans_type` = &#039;Thu&#039;\n<strong>AND<\/strong> `status` = 1\n<strong>AND<\/strong> `trans_date` &gt;= &#039;2023-10-19 00:00:00&#039;\n<strong>AND<\/strong> `trans_date` &lt;= &#039;2023-10-19 15:30:45&#039;"},{"name":"Query","component":"Database","start":1697704245.27704,"duration":"0.000164","query":"<strong>SELECT<\/strong> <strong>SUM<\/strong>(money) as money\n<strong>FROM<\/strong> `trans`\n<strong>WHERE<\/strong> `trans_type` = &#039;Thu&#039;\n<strong>AND<\/strong> `status` = 1\n<strong>AND<\/strong> `trans_date` &gt;= &#039;2023-10-19 00:00:00&#039;\n<strong>AND<\/strong> `trans_date` &lt;= &#039;2023-10-19 15:30:45&#039;"},{"name":"Query","component":"Database","start":1697704245.277302,"duration":"0.000209","query":"<strong>SELECT<\/strong> <strong>COUNT<\/strong>(`trans_id`) <strong>AS<\/strong> `trans_id`\n<strong>FROM<\/strong> `trans`\n<strong>WHERE<\/strong> `trans_type` = &#039;Chi&#039;\n<strong>AND<\/strong> `status` = 1\n<strong>AND<\/strong> `trans_date` &gt;= &#039;2023-10-19 00:00:00&#039;\n<strong>AND<\/strong> `trans_date` &lt;= &#039;2023-10-19 15:30:45&#039;"},{"name":"Query","component":"Database","start":1697704245.277597,"duration":"0.000186","query":"<strong>SELECT<\/strong> <strong>SUM<\/strong>(money) as money\n<strong>FROM<\/strong> `trans`\n<strong>WHERE<\/strong> `trans_type` = &#039;Chi&#039;\n<strong>AND<\/strong> `status` = 1\n<strong>AND<\/strong> `trans_date` &gt;= &#039;2023-10-19 00:00:00&#039;\n<strong>AND<\/strong> `trans_date` &lt;= &#039;2023-10-19 15:30:45&#039;"},{"name":"Query","component":"Database","start":1697704245.277853,"duration":"0.000218","query":"<strong>SELECT<\/strong> *\n<strong>FROM<\/strong> `bill_detail`\n<strong>WHERE<\/strong> `bill_id` = &#039;21&#039;"},{"name":"Query","component":"Database","start":1697704245.278128,"duration":"0.000157","query":"<strong>SELECT<\/strong> *\n<strong>FROM<\/strong> `bill_detail`\n<strong>WHERE<\/strong> `bill_id` = &#039;22&#039;"},{"name":"Query","component":"Database","start":1697704245.278342,"duration":"0.000142","query":"<strong>SELECT<\/strong> *\n<strong>FROM<\/strong> `bill_detail`\n<strong>WHERE<\/strong> `bill_id` = &#039;23&#039;"},{"name":"Query","component":"Database","start":1697704245.278534,"duration":"0.000131","query":"<strong>SELECT<\/strong> *\n<strong>FROM<\/strong> `bill_detail`\n<strong>WHERE<\/strong> `bill_id` = &#039;24&#039;"},{"name":"Query","component":"Database","start":1697704245.278723,"duration":"0.000162","query":"<strong>SELECT<\/strong> *\n<strong>FROM<\/strong> `bill_detail`\n<strong>WHERE<\/strong> `bill_id` = &#039;25&#039;"},{"name":"Query","component":"Database","start":1697704245.278932,"duration":"0.000153","query":"<strong>SELECT<\/strong> *\n<strong>FROM<\/strong> `bill_detail`\n<strong>WHERE<\/strong> `bill_id` = &#039;27&#039;"},{"name":"Query","component":"Database","start":1697704245.279146,"duration":"0.000173","query":"<strong>SELECT<\/strong> `food_id`, `food_name`, `description`, `status`, `catalog_id`\n<strong>FROM<\/strong> `food`"},{"name":"Query","component":"Database","start":1697704245.279394,"duration":"0.000155","query":"<strong>SELECT<\/strong> <strong>COUNT<\/strong>(`bill_detail_id`) <strong>AS<\/strong> `bill_detail_id`\n<strong>FROM<\/strong> `bill_detail`\n<strong>WHERE<\/strong> `food_id` = &#039;1&#039;\n<strong>AND<\/strong> `bill_id` <strong>IN<\/strong> (&#039;21&#039;,&#039;22&#039;,&#039;23&#039;,&#039;24&#039;,&#039;25&#039;,&#039;27&#039;)"},{"name":"Query","component":"Database","start":1697704245.279613,"duration":"0.000149","query":"<strong>SELECT<\/strong> <strong>SUM<\/strong>(count) as count\n<strong>FROM<\/strong> `bill_detail`\n<strong>WHERE<\/strong> `food_id` = &#039;1&#039;\n<strong>AND<\/strong> `bill_id` <strong>IN<\/strong> (&#039;21&#039;,&#039;22&#039;,&#039;23&#039;,&#039;24&#039;,&#039;25&#039;,&#039;27&#039;)"},{"name":"Query","component":"Database","start":1697704245.279829,"duration":"0.000123","query":"<strong>SELECT<\/strong> <strong>COUNT<\/strong>(`bill_detail_id`) <strong>AS<\/strong> `bill_detail_id`\n<strong>FROM<\/strong> `bill_detail`\n<strong>WHERE<\/strong> `food_id` = &#039;2&#039;\n<strong>AND<\/strong> `bill_id` <strong>IN<\/strong> (&#039;21&#039;,&#039;22&#039;,&#039;23&#039;,&#039;24&#039;,&#039;25&#039;,&#039;27&#039;)"},{"name":"Query","component":"Database","start":1697704245.280005,"duration":"0.000117","query":"<strong>SELECT<\/strong> <strong>SUM<\/strong>(count) as count\n<strong>FROM<\/strong> `bill_detail`\n<strong>WHERE<\/strong> `food_id` = &#039;2&#039;\n<strong>AND<\/strong> `bill_id` <strong>IN<\/strong> (&#039;21&#039;,&#039;22&#039;,&#039;23&#039;,&#039;24&#039;,&#039;25&#039;,&#039;27&#039;)"},{"name":"Query","component":"Database","start":1697704245.280179,"duration":"0.000116","query":"<strong>SELECT<\/strong> <strong>COUNT<\/strong>(`bill_detail_id`) <strong>AS<\/strong> `bill_detail_id`\n<strong>FROM<\/strong> `bill_detail`\n<strong>WHERE<\/strong> `food_id` = &#039;3&#039;\n<strong>AND<\/strong> `bill_id` <strong>IN<\/strong> (&#039;21&#039;,&#039;22&#039;,&#039;23&#039;,&#039;24&#039;,&#039;25&#039;,&#039;27&#039;)"},{"name":"Query","component":"Database","start":1697704245.280343,"duration":"0.000118","query":"<strong>SELECT<\/strong> <strong>SUM<\/strong>(count) as count\n<strong>FROM<\/strong> `bill_detail`\n<strong>WHERE<\/strong> `food_id` = &#039;3&#039;\n<strong>AND<\/strong> `bill_id` <strong>IN<\/strong> (&#039;21&#039;,&#039;22&#039;,&#039;23&#039;,&#039;24&#039;,&#039;25&#039;,&#039;27&#039;)"},{"name":"Query","component":"Database","start":1697704245.28053,"duration":"0.000129","query":"<strong>SELECT<\/strong> <strong>COUNT<\/strong>(`bill_detail_id`) <strong>AS<\/strong> `bill_detail_id`\n<strong>FROM<\/strong> `bill_detail`\n<strong>WHERE<\/strong> `food_id` = &#039;4&#039;\n<strong>AND<\/strong> `bill_id` <strong>IN<\/strong> (&#039;21&#039;,&#039;22&#039;,&#039;23&#039;,&#039;24&#039;,&#039;25&#039;,&#039;27&#039;)"},{"name":"Query","component":"Database","start":1697704245.280712,"duration":"0.000116","query":"<strong>SELECT<\/strong> <strong>SUM<\/strong>(count) as count\n<strong>FROM<\/strong> `bill_detail`\n<strong>WHERE<\/strong> `food_id` = &#039;4&#039;\n<strong>AND<\/strong> `bill_id` <strong>IN<\/strong> (&#039;21&#039;,&#039;22&#039;,&#039;23&#039;,&#039;24&#039;,&#039;25&#039;,&#039;27&#039;)"}]},{"title":"Logs","titleSafe":"logs","titleDetails":"","display":{"logs":[]},"badgeValue":null,"isEmpty":true,"hasTabContent":true,"hasLabel":false,"icon":"data:image\/png;base64,iVBORw0KGgoAAAANSUhEUgAAABgAAAAYCAYAAADgdz34AAAAAXNSR0IArs4c6QAAAARnQU1BAACxjwv8YQUAAAAJcEhZcwAADsMAAA7DAcdvqGQAAACYSURBVEhLYxgFJIHU1FSjtLS0i0D8AYj7gEKMEBkqAaAFF4D4ERCvAFrwH4gDoFIMKSkpFkB+OTEYqgUTACXfA\/GqjIwMQyD9H2hRHlQKJFcBEiMGQ7VgAqCBvUgK32dmZspCpagGGNPT0\/1BLqeF4bQHQJePpiIwhmrBBEADR1MRfgB0+WgqAmOoFkwANHA0FY0CUgEDAwCQ0PUpNB3kqwAAAABJRU5ErkJggg==","hasTimelineData":false,"timelineData":[]},{"title":"Views","titleSafe":"views","titleDetails":"","display":[],"badgeValue":0,"isEmpty":false,"hasTabContent":false,"hasLabel":true,"icon":"data:image\/png;base64,iVBORw0KGgoAAAANSUhEUgAAABgAAAAYCAYAAADgdz34AAAAAXNSR0IArs4c6QAAAARnQU1BAACxjwv8YQUAAAAJcEhZcwAADsMAAA7DAcdvqGQAAADeSURBVEhL7ZSxDcIwEEWNYA0YgGmgyAaJLTcUaaBzQQEVjMEabBQxAdw53zTHiThEovGTfnE\/9rsoRUxhKLOmaa6Uh7X2+UvguLCzVxN1XW9x4EYHzik033Hp3X0LO+DaQG8MDQcuq6qao4qkHuMgQggLvkPLjqh00ZgFDBacMJYFkuwFlH1mshdkZ5JPJERA9JpI6xNCBESvibQ+IURA9JpI6xNCBESvibQ+IURA9DTsuHTOrVFFxixgB\/eUFlU8uKJ0eDBFOu\/9EvoeKnlJS2\/08Tc8NOwQ8sIfMeYFjqKDjdU2sp4AAAAASUVORK5CYII=","hasTimelineData":true,"timelineData":[]},{"title":"Files","titleSafe":"files","titleDetails":"( 131 )","display":{"coreFiles":[{"name":"AbstractRenderer.php","path":"SYSTEMPATH\\ThirdParty\\Kint\\Renderer\\AbstractRenderer.php"},{"name":"AutoloadConfig.php","path":"SYSTEMPATH\\Config\\AutoloadConfig.php"},{"name":"Autoloader.php","path":"SYSTEMPATH\\Autoloader\\Autoloader.php"},{"name":"BaseBuilder.php","path":"SYSTEMPATH\\Database\\BaseBuilder.php"},{"name":"BaseCollector.php","path":"SYSTEMPATH\\Debug\\Toolbar\\Collectors\\BaseCollector.php"},{"name":"BaseConfig.php","path":"SYSTEMPATH\\Config\\BaseConfig.php"},{"name":"BaseConnection.php","path":"SYSTEMPATH\\Database\\BaseConnection.php"},{"name":"BaseHandler.php","path":"SYSTEMPATH\\Cache\\Handlers\\BaseHandler.php"},{"name":"BaseModel.php","path":"SYSTEMPATH\\BaseModel.php"},{"name":"BaseResult.php","path":"SYSTEMPATH\\Database\\BaseResult.php"},{"name":"BaseService.php","path":"SYSTEMPATH\\Config\\BaseService.php"},{"name":"Builder.php","path":"SYSTEMPATH\\Database\\MySQLi\\Builder.php"},{"name":"CacheFactory.php","path":"SYSTEMPATH\\Cache\\CacheFactory.php"},{"name":"CacheInterface.php","path":"SYSTEMPATH\\Cache\\CacheInterface.php"},{"name":"CliRenderer.php","path":"SYSTEMPATH\\ThirdParty\\Kint\\Renderer\\CliRenderer.php"},{"name":"CloneableCookieInterface.php","path":"SYSTEMPATH\\Cookie\\CloneableCookieInterface.php"},{"name":"CodeIgniter.php","path":"SYSTEMPATH\\CodeIgniter.php"},{"name":"Common.php","path":"SYSTEMPATH\\Common.php"},{"name":"ConditionalTrait.php","path":"SYSTEMPATH\\Traits\\ConditionalTrait.php"},{"name":"Config.php","path":"SYSTEMPATH\\Database\\Config.php"},{"name":"Connection.php","path":"SYSTEMPATH\\Database\\MySQLi\\Connection.php"},{"name":"ConnectionInterface.php","path":"SYSTEMPATH\\Database\\ConnectionInterface.php"},{"name":"ContentSecurityPolicy.php","path":"SYSTEMPATH\\HTTP\\ContentSecurityPolicy.php"},{"name":"Controller.php","path":"SYSTEMPATH\\Controller.php"},{"name":"Cookie.php","path":"SYSTEMPATH\\Cookie\\Cookie.php"},{"name":"CookieInterface.php","path":"SYSTEMPATH\\Cookie\\CookieInterface.php"},{"name":"CookieStore.php","path":"SYSTEMPATH\\Cookie\\CookieStore.php"},{"name":"Database.php","path":"SYSTEMPATH\\Database\\Database.php"},{"name":"Database.php","path":"SYSTEMPATH\\Debug\\Toolbar\\Collectors\\Database.php"},{"name":"DebugToolbar.php","path":"SYSTEMPATH\\Filters\\DebugToolbar.php"},{"name":"DotEnv.php","path":"SYSTEMPATH\\Config\\DotEnv.php"},{"name":"Escaper.php","path":"SYSTEMPATH\\ThirdParty\\Escaper\\Escaper.php"},{"name":"Events.php","path":"SYSTEMPATH\\Debug\\Toolbar\\Collectors\\Events.php"},{"name":"Events.php","path":"SYSTEMPATH\\Events\\Events.php"},{"name":"Exceptions.php","path":"SYSTEMPATH\\Debug\\Exceptions.php"},{"name":"FacadeInterface.php","path":"SYSTEMPATH\\ThirdParty\\Kint\\FacadeInterface.php"},{"name":"Factories.php","path":"SYSTEMPATH\\Config\\Factories.php"},{"name":"Factory.php","path":"SYSTEMPATH\\Config\\Factory.php"},{"name":"FileHandler.php","path":"SYSTEMPATH\\Cache\\Handlers\\FileHandler.php"},{"name":"FileLocator.php","path":"SYSTEMPATH\\Autoloader\\FileLocator.php"},{"name":"Files.php","path":"SYSTEMPATH\\Debug\\Toolbar\\Collectors\\Files.php"},{"name":"FilterInterface.php","path":"SYSTEMPATH\\Filters\\FilterInterface.php"},{"name":"Filters.php","path":"SYSTEMPATH\\Filters\\Filters.php"},{"name":"Header.php","path":"SYSTEMPATH\\HTTP\\Header.php"},{"name":"IncomingRequest.php","path":"SYSTEMPATH\\HTTP\\IncomingRequest.php"},{"name":"Kint.php","path":"SYSTEMPATH\\ThirdParty\\Kint\\Kint.php"},{"name":"LogLevel.php","path":"SYSTEMPATH\\ThirdParty\\PSR\\Log\\LogLevel.php"},{"name":"Logger.php","path":"SYSTEMPATH\\Log\\Logger.php"},{"name":"LoggerInterface.php","path":"SYSTEMPATH\\ThirdParty\\PSR\\Log\\LoggerInterface.php"},{"name":"Logs.php","path":"SYSTEMPATH\\Debug\\Toolbar\\Collectors\\Logs.php"},{"name":"Message.php","path":"SYSTEMPATH\\HTTP\\Message.php"},{"name":"MessageInterface.php","path":"SYSTEMPATH\\HTTP\\MessageInterface.php"},{"name":"MessageTrait.php","path":"SYSTEMPATH\\HTTP\\MessageTrait.php"},{"name":"Model.php","path":"SYSTEMPATH\\Model.php"},{"name":"Modules.php","path":"SYSTEMPATH\\Modules\\Modules.php"},{"name":"OutgoingRequest.php","path":"SYSTEMPATH\\HTTP\\OutgoingRequest.php"},{"name":"OutgoingRequestInterface.php","path":"SYSTEMPATH\\HTTP\\OutgoingRequestInterface.php"},{"name":"Query.php","path":"SYSTEMPATH\\Database\\Query.php"},{"name":"QueryInterface.php","path":"SYSTEMPATH\\Database\\QueryInterface.php"},{"name":"RendererInterface.php","path":"SYSTEMPATH\\ThirdParty\\Kint\\Renderer\\RendererInterface.php"},{"name":"RendererInterface.php","path":"SYSTEMPATH\\View\\RendererInterface.php"},{"name":"Request.php","path":"SYSTEMPATH\\HTTP\\Request.php"},{"name":"RequestInterface.php","path":"SYSTEMPATH\\HTTP\\RequestInterface.php"},{"name":"RequestTrait.php","path":"SYSTEMPATH\\HTTP\\RequestTrait.php"},{"name":"Response.php","path":"SYSTEMPATH\\HTTP\\Response.php"},{"name":"ResponseInterface.php","path":"SYSTEMPATH\\HTTP\\ResponseInterface.php"},{"name":"ResponseTrait.php","path":"SYSTEMPATH\\API\\ResponseTrait.php"},{"name":"ResponseTrait.php","path":"SYSTEMPATH\\HTTP\\ResponseTrait.php"},{"name":"Result.php","path":"SYSTEMPATH\\Database\\MySQLi\\Result.php"},{"name":"ResultInterface.php","path":"SYSTEMPATH\\Database\\ResultInterface.php"},{"name":"RichRenderer.php","path":"SYSTEMPATH\\ThirdParty\\Kint\\Renderer\\RichRenderer.php"},{"name":"RouteCollection.php","path":"SYSTEMPATH\\Router\\RouteCollection.php"},{"name":"RouteCollectionInterface.php","path":"SYSTEMPATH\\Router\\RouteCollectionInterface.php"},{"name":"Router.php","path":"SYSTEMPATH\\Router\\Router.php"},{"name":"RouterInterface.php","path":"SYSTEMPATH\\Router\\RouterInterface.php"},{"name":"Routes.php","path":"SYSTEMPATH\\Debug\\Toolbar\\Collectors\\Routes.php"},{"name":"Services.php","path":"SYSTEMPATH\\Config\\Services.php"},{"name":"TextRenderer.php","path":"SYSTEMPATH\\ThirdParty\\Kint\\Renderer\\TextRenderer.php"},{"name":"Time.php","path":"SYSTEMPATH\\I18n\\Time.php"},{"name":"TimeTrait.php","path":"SYSTEMPATH\\I18n\\TimeTrait.php"},{"name":"Timer.php","path":"SYSTEMPATH\\Debug\\Timer.php"},{"name":"Timers.php","path":"SYSTEMPATH\\Debug\\Toolbar\\Collectors\\Timers.php"},{"name":"Toolbar.php","path":"SYSTEMPATH\\Debug\\Toolbar.php"},{"name":"URI.php","path":"SYSTEMPATH\\HTTP\\URI.php"},{"name":"UserAgent.php","path":"SYSTEMPATH\\HTTP\\UserAgent.php"},{"name":"Utils.php","path":"SYSTEMPATH\\ThirdParty\\Kint\\Utils.php"},{"name":"Validation.php","path":"SYSTEMPATH\\Validation\\Validation.php"},{"name":"ValidationInterface.php","path":"SYSTEMPATH\\Validation\\ValidationInterface.php"},{"name":"View.php","path":"SYSTEMPATH\\Config\\View.php"},{"name":"View.php","path":"SYSTEMPATH\\View\\View.php"},{"name":"ViewDecoratorTrait.php","path":"SYSTEMPATH\\View\\ViewDecoratorTrait.php"},{"name":"Views.php","path":"SYSTEMPATH\\Debug\\Toolbar\\Collectors\\Views.php"},{"name":"array_helper.php","path":"SYSTEMPATH\\Helpers\\array_helper.php"},{"name":"bootstrap.php","path":"SYSTEMPATH\\bootstrap.php"},{"name":"cookie_helper.php","path":"SYSTEMPATH\\Helpers\\cookie_helper.php"},{"name":"form_helper.php","path":"SYSTEMPATH\\Helpers\\form_helper.php"},{"name":"html_helper.php","path":"SYSTEMPATH\\Helpers\\html_helper.php"},{"name":"init.php","path":"SYSTEMPATH\\ThirdParty\\Kint\\init.php"},{"name":"init_helpers.php","path":"SYSTEMPATH\\ThirdParty\\Kint\\init_helpers.php"},{"name":"kint_helper.php","path":"SYSTEMPATH\\Helpers\\kint_helper.php"},{"name":"url_helper.php","path":"SYSTEMPATH\\Helpers\\url_helper.php"}],"userFiles":[{"name":"App.php","path":"APPPATH\\Config\\App.php"},{"name":"Autoload.php","path":"APPPATH\\Config\\Autoload.php"},{"name":"BaseController.php","path":"APPPATH\\Controllers\\BaseController.php"},{"name":"BillDetailModel.php","path":"APPPATH\\Models\\BillDetailModel.php"},{"name":"BillModel.php","path":"APPPATH\\Models\\BillModel.php"},{"name":"Cache.php","path":"APPPATH\\Config\\Cache.php"},{"name":"Common.php","path":"APPPATH\\Common.php"},{"name":"Constants.php","path":"APPPATH\\Config\\Constants.php"},{"name":"ContentSecurityPolicy.php","path":"APPPATH\\Config\\ContentSecurityPolicy.php"},{"name":"Cookie.php","path":"APPPATH\\Config\\Cookie.php"},{"name":"Database.php","path":"APPPATH\\Config\\Database.php"},{"name":"Events.php","path":"APPPATH\\Config\\Events.php"},{"name":"Exceptions.php","path":"APPPATH\\Config\\Exceptions.php"},{"name":"Feature.php","path":"APPPATH\\Config\\Feature.php"},{"name":"Filters.php","path":"APPPATH\\Config\\Filters.php"},{"name":"FoodModel.php","path":"APPPATH\\Models\\FoodModel.php"},{"name":"Home.php","path":"APPPATH\\Controllers\\Home.php"},{"name":"Kint.php","path":"APPPATH\\Config\\Kint.php"},{"name":"Logger.php","path":"APPPATH\\Config\\Logger.php"},{"name":"Modules.php","path":"APPPATH\\Config\\Modules.php"},{"name":"Paths.php","path":"APPPATH\\Config\\Paths.php"},{"name":"Routes.php","path":"APPPATH\\Config\\Routes.php"},{"name":"Services.php","path":"APPPATH\\Config\\Services.php"},{"name":"Toolbar.php","path":"APPPATH\\Config\\Toolbar.php"},{"name":"TransModel.php","path":"APPPATH\\Models\\TransModel.php"},{"name":"UserAgents.php","path":"APPPATH\\Config\\UserAgents.php"},{"name":"Validation.php","path":"APPPATH\\Config\\Validation.php"},{"name":"View.php","path":"APPPATH\\Config\\View.php"},{"name":"development.php","path":"APPPATH\\Config\\Boot\\development.php"},{"name":"index.php","path":"FCPATH\\index.php"}]},"badgeValue":131,"isEmpty":false,"hasTabContent":true,"hasLabel":false,"icon":"data:image\/png;base64,iVBORw0KGgoAAAANSUhEUgAAABgAAAAYCAYAAADgdz34AAAAAXNSR0IArs4c6QAAAARnQU1BAACxjwv8YQUAAAAJcEhZcwAADsMAAA7DAcdvqGQAAAGBSURBVEhL7ZQ9S8NQGIVTBQUncfMfCO4uLgoKbuKQOWg+OkXERRE1IAXrIHbVDrqIDuLiJgj+gro7S3dnpfq88b1FMTE3VZx64HBzzvvZWxKnj15QCcPwCD5HUfSWR+JtzgmtsUcQBEva5IIm9SwSu+95CAWbUuy67qBa32ByZEDpIaZYZSZMjjQuPcQUq8yEyYEb8FSerYeQVGbAFzJkX1PyQWLhgCz0BxTCekC1Wp0hsa6yokzhed4oje6Iz6rlJEkyIKfUEFtITVtQdAibn5rMyaYsMS+a5wTv8qeXMhcU16QZbKgl3hbs+L4\/pnpdc87MElZgq10p5DxGdq8I7xrvUWUKvG3NbSK7ubngYzdJwSsF7TiOh9VOgfcEz1UayNe3JUPM1RWC5GXYgTfc75B4NBmXJnAtTfpABX0iPvEd9ezALwkplCFXcr9styiNOKc1RRZpaPM9tcqBwlWzGY1qPL9wjqRBgF5BH6j8HWh2S7MHlX8PrmbK+k\/8PzjOOzx1D3i1pKTTAAAAAElFTkSuQmCC","hasTimelineData":false,"timelineData":[]},{"title":"Routes","titleSafe":"routes","titleDetails":"","display":{"matchedRoute":[{"directory":"","controller":"\\App\\Controllers\\Home","method":"reports","paramCount":0,"truePCount":0,"params":[]}],"routes":[{"method":"GET","route":"\/","handler":"\\App\\Controllers\\Home::index"},{"method":"GET","route":"views","handler":"\\App\\Controllers\\Home::views"},{"method":"GET","route":"load","handler":"\\App\\Controllers\\Home::load"},{"method":"GET","route":"detailLoad","handler":"\\App\\Controllers\\Home::detailLoad"},{"method":"GET","route":"testData","handler":"\\App\\Controllers\\Home::testData"},{"method":"GET","route":"getOptionsOfOrderGrid","handler":"\\App\\Controllers\\Home::getOptionsOfOrderGrid"},{"method":"GET","route":"getDataToAddForm","handler":"\\App\\Controllers\\Home::getDataToAddForm"},{"method":"GET","route":"getDetailDataToAdd","handler":"\\App\\Controllers\\Home::getDetailDataToAdd"},{"method":"GET","route":"getAreaId","handler":"\\App\\Controllers\\Home::getAreaId"},{"method":"GET","route":"getFoodPrice","handler":"\\App\\Controllers\\Home::getFoodPrice"},{"method":"GET","route":"saveOrder","handler":"\\App\\Controllers\\Home::saveOrder"},{"method":"GET","route":"saveMainOrder","handler":"\\App\\Controllers\\Home::saveMainOrder"},{"method":"GET","route":"deleteMainOrder","handler":"\\App\\Controllers\\Home::deleteMainOrder"},{"method":"GET","route":"saveDetail","handler":"\\App\\Controllers\\Home::saveDetail"},{"method":"GET","route":"deleteDetail","handler":"\\App\\Controllers\\Home::deleteDetail"},{"method":"GET","route":"printer","handler":"\\App\\Controllers\\Home::printer"},{"method":"GET","route":"area","handler":"\\App\\Controllers\\Home::area"},{"method":"GET","route":"saveArea","handler":"\\App\\Controllers\\Home::saveArea"},{"method":"GET","route":"deleteArea","handler":"\\App\\Controllers\\Home::deleteArea"},{"method":"GET","route":"tableOrder","handler":"\\App\\Controllers\\Home::tableOrder"},{"method":"GET","route":"saveTableOrder","handler":"\\App\\Controllers\\Home::saveTableOrder"},{"method":"GET","route":"deleteTableOrder","handler":"\\App\\Controllers\\Home::deleteTableOrder"},{"method":"GET","route":"food","handler":"\\App\\Controllers\\Home::food"},{"method":"GET","route":"saveFood","handler":"\\App\\Controllers\\Home::saveFood"},{"method":"GET","route":"deleteFood","handler":"\\App\\Controllers\\Home::deleteFood"},{"method":"GET","route":"promotion","handler":"\\App\\Controllers\\Home::promotion"},{"method":"GET","route":"savePromotion","handler":"\\App\\Controllers\\Home::savePromotion"},{"method":"GET","route":"deletePromotion","handler":"\\App\\Controllers\\Home::deletePromotion"},{"method":"GET","route":"size","handler":"\\App\\Controllers\\Home::size"},{"method":"GET","route":"saveSize","handler":"\\App\\Controllers\\Home::saveSize"},{"method":"GET","route":"deleteSize","handler":"\\App\\Controllers\\Home::deleteSize"},{"method":"GET","route":"unit","handler":"\\App\\Controllers\\Home::unit"},{"method":"GET","route":"saveUnit","handler":"\\App\\Controllers\\Home::saveUnit"},{"method":"GET","route":"deleteUnit","handler":"\\App\\Controllers\\Home::deleteUnit"},{"method":"GET","route":"sizeUnit","handler":"\\App\\Controllers\\Home::sizeUnit"},{"method":"GET","route":"updateUnitSizeAuto","handler":"\\App\\Controllers\\Home::updateUnitSizeAuto"},{"method":"GET","route":"transaction","handler":"\\App\\Controllers\\Home::transaction"},{"method":"GET","route":"saveTransaction","handler":"\\App\\Controllers\\Home::saveTransaction"},{"method":"GET","route":"deleteTransaction","handler":"\\App\\Controllers\\Home::deleteTransaction"},{"method":"GET","route":"reports","handler":"\\App\\Controllers\\Home::reports"},{"method":"GET","route":"imports","handler":"\\App\\Controllers\\Home::imports"},{"method":"HEAD","route":"getDataToAddForm","handler":"\\App\\Controllers\\Home::getDataToAddForm"},{"method":"HEAD","route":"getDetailDataToAdd","handler":"\\App\\Controllers\\Home::getDetailDataToAdd"},{"method":"HEAD","route":"getAreaId","handler":"\\App\\Controllers\\Home::getAreaId"},{"method":"HEAD","route":"getFoodPrice","handler":"\\App\\Controllers\\Home::getFoodPrice"},{"method":"HEAD","route":"saveOrder","handler":"\\App\\Controllers\\Home::saveOrder"},{"method":"HEAD","route":"saveMainOrder","handler":"\\App\\Controllers\\Home::saveMainOrder"},{"method":"HEAD","route":"deleteMainOrder","handler":"\\App\\Controllers\\Home::deleteMainOrder"},{"method":"HEAD","route":"saveDetail","handler":"\\App\\Controllers\\Home::saveDetail"},{"method":"HEAD","route":"deleteDetail","handler":"\\App\\Controllers\\Home::deleteDetail"},{"method":"HEAD","route":"printer","handler":"\\App\\Controllers\\Home::printer"},{"method":"HEAD","route":"area","handler":"\\App\\Controllers\\Home::area"},{"method":"HEAD","route":"saveArea","handler":"\\App\\Controllers\\Home::saveArea"},{"method":"HEAD","route":"deleteArea","handler":"\\App\\Controllers\\Home::deleteArea"},{"method":"HEAD","route":"tableOrder","handler":"\\App\\Controllers\\Home::tableOrder"},{"method":"HEAD","route":"saveTableOrder","handler":"\\App\\Controllers\\Home::saveTableOrder"},{"method":"HEAD","route":"deleteTableOrder","handler":"\\App\\Controllers\\Home::deleteTableOrder"},{"method":"HEAD","route":"food","handler":"\\App\\Controllers\\Home::food"},{"method":"HEAD","route":"saveFood","handler":"\\App\\Controllers\\Home::saveFood"},{"method":"HEAD","route":"deleteFood","handler":"\\App\\Controllers\\Home::deleteFood"},{"method":"HEAD","route":"promotion","handler":"\\App\\Controllers\\Home::promotion"},{"method":"HEAD","route":"savePromotion","handler":"\\App\\Controllers\\Home::savePromotion"},{"method":"HEAD","route":"deletePromotion","handler":"\\App\\Controllers\\Home::deletePromotion"},{"method":"HEAD","route":"size","handler":"\\App\\Controllers\\Home::size"},{"method":"HEAD","route":"saveSize","handler":"\\App\\Controllers\\Home::saveSize"},{"method":"HEAD","route":"deleteSize","handler":"\\App\\Controllers\\Home::deleteSize"},{"method":"HEAD","route":"unit","handler":"\\App\\Controllers\\Home::unit"},{"method":"HEAD","route":"saveUnit","handler":"\\App\\Controllers\\Home::saveUnit"},{"method":"HEAD","route":"deleteUnit","handler":"\\App\\Controllers\\Home::deleteUnit"},{"method":"HEAD","route":"sizeUnit","handler":"\\App\\Controllers\\Home::sizeUnit"},{"method":"HEAD","route":"updateUnitSizeAuto","handler":"\\App\\Controllers\\Home::updateUnitSizeAuto"},{"method":"HEAD","route":"transaction","handler":"\\App\\Controllers\\Home::transaction"},{"method":"HEAD","route":"saveTransaction","handler":"\\App\\Controllers\\Home::saveTransaction"},{"method":"HEAD","route":"deleteTransaction","handler":"\\App\\Controllers\\Home::deleteTransaction"},{"method":"HEAD","route":"reports","handler":"\\App\\Controllers\\Home::reports"},{"method":"HEAD","route":"imports","handler":"\\App\\Controllers\\Home::imports"},{"method":"POST","route":"getDataToAddForm","handler":"\\App\\Controllers\\Home::getDataToAddForm"},{"method":"POST","route":"getDetailDataToAdd","handler":"\\App\\Controllers\\Home::getDetailDataToAdd"},{"method":"POST","route":"getAreaId","handler":"\\App\\Controllers\\Home::getAreaId"},{"method":"POST","route":"getFoodPrice","handler":"\\App\\Controllers\\Home::getFoodPrice"},{"method":"POST","route":"saveOrder","handler":"\\App\\Controllers\\Home::saveOrder"},{"method":"POST","route":"saveMainOrder","handler":"\\App\\Controllers\\Home::saveMainOrder"},{"method":"POST","route":"deleteMainOrder","handler":"\\App\\Controllers\\Home::deleteMainOrder"},{"method":"POST","route":"saveDetail","handler":"\\App\\Controllers\\Home::saveDetail"},{"method":"POST","route":"deleteDetail","handler":"\\App\\Controllers\\Home::deleteDetail"},{"method":"POST","route":"printer","handler":"\\App\\Controllers\\Home::printer"},{"method":"POST","route":"area","handler":"\\App\\Controllers\\Home::area"},{"method":"POST","route":"saveArea","handler":"\\App\\Controllers\\Home::saveArea"},{"method":"POST","route":"deleteArea","handler":"\\App\\Controllers\\Home::deleteArea"},{"method":"POST","route":"tableOrder","handler":"\\App\\Controllers\\Home::tableOrder"},{"method":"POST","route":"saveTableOrder","handler":"\\App\\Controllers\\Home::saveTableOrder"},{"method":"POST","route":"deleteTableOrder","handler":"\\App\\Controllers\\Home::deleteTableOrder"},{"method":"POST","route":"food","handler":"\\App\\Controllers\\Home::food"},{"method":"POST","route":"saveFood","handler":"\\App\\Controllers\\Home::saveFood"},{"method":"POST","route":"deleteFood","handler":"\\App\\Controllers\\Home::deleteFood"},{"method":"POST","route":"promotion","handler":"\\App\\Controllers\\Home::promotion"},{"method":"POST","route":"savePromotion","handler":"\\App\\Controllers\\Home::savePromotion"},{"method":"POST","route":"deletePromotion","handler":"\\App\\Controllers\\Home::deletePromotion"},{"method":"POST","route":"size","handler":"\\App\\Controllers\\Home::size"},{"method":"POST","route":"saveSize","handler":"\\App\\Controllers\\Home::saveSize"},{"method":"POST","route":"deleteSize","handler":"\\App\\Controllers\\Home::deleteSize"},{"method":"POST","route":"unit","handler":"\\App\\Controllers\\Home::unit"},{"method":"POST","route":"saveUnit","handler":"\\App\\Controllers\\Home::saveUnit"},{"method":"POST","route":"deleteUnit","handler":"\\App\\Controllers\\Home::deleteUnit"},{"method":"POST","route":"sizeUnit","handler":"\\App\\Controllers\\Home::sizeUnit"},{"method":"POST","route":"updateUnitSizeAuto","handler":"\\App\\Controllers\\Home::updateUnitSizeAuto"},{"method":"POST","route":"transaction","handler":"\\App\\Controllers\\Home::transaction"},{"method":"POST","route":"saveTransaction","handler":"\\App\\Controllers\\Home::saveTransaction"},{"method":"POST","route":"deleteTransaction","handler":"\\App\\Controllers\\Home::deleteTransaction"},{"method":"POST","route":"reports","handler":"\\App\\Controllers\\Home::reports"},{"method":"POST","route":"imports","handler":"\\App\\Controllers\\Home::imports"},{"method":"PUT","route":"getDataToAddForm","handler":"\\App\\Controllers\\Home::getDataToAddForm"},{"method":"PUT","route":"getDetailDataToAdd","handler":"\\App\\Controllers\\Home::getDetailDataToAdd"},{"method":"PUT","route":"getAreaId","handler":"\\App\\Controllers\\Home::getAreaId"},{"method":"PUT","route":"getFoodPrice","handler":"\\App\\Controllers\\Home::getFoodPrice"},{"method":"PUT","route":"saveOrder","handler":"\\App\\Controllers\\Home::saveOrder"},{"method":"PUT","route":"saveMainOrder","handler":"\\App\\Controllers\\Home::saveMainOrder"},{"method":"PUT","route":"deleteMainOrder","handler":"\\App\\Controllers\\Home::deleteMainOrder"},{"method":"PUT","route":"saveDetail","handler":"\\App\\Controllers\\Home::saveDetail"},{"method":"PUT","route":"deleteDetail","handler":"\\App\\Controllers\\Home::deleteDetail"},{"method":"PUT","route":"printer","handler":"\\App\\Controllers\\Home::printer"},{"method":"PUT","route":"area","handler":"\\App\\Controllers\\Home::area"},{"method":"PUT","route":"saveArea","handler":"\\App\\Controllers\\Home::saveArea"},{"method":"PUT","route":"deleteArea","handler":"\\App\\Controllers\\Home::deleteArea"},{"method":"PUT","route":"tableOrder","handler":"\\App\\Controllers\\Home::tableOrder"},{"method":"PUT","route":"saveTableOrder","handler":"\\App\\Controllers\\Home::saveTableOrder"},{"method":"PUT","route":"deleteTableOrder","handler":"\\App\\Controllers\\Home::deleteTableOrder"},{"method":"PUT","route":"food","handler":"\\App\\Controllers\\Home::food"},{"method":"PUT","route":"saveFood","handler":"\\App\\Controllers\\Home::saveFood"},{"method":"PUT","route":"deleteFood","handler":"\\App\\Controllers\\Home::deleteFood"},{"method":"PUT","route":"promotion","handler":"\\App\\Controllers\\Home::promotion"},{"method":"PUT","route":"savePromotion","handler":"\\App\\Controllers\\Home::savePromotion"},{"method":"PUT","route":"deletePromotion","handler":"\\App\\Controllers\\Home::deletePromotion"},{"method":"PUT","route":"size","handler":"\\App\\Controllers\\Home::size"},{"method":"PUT","route":"saveSize","handler":"\\App\\Controllers\\Home::saveSize"},{"method":"PUT","route":"deleteSize","handler":"\\App\\Controllers\\Home::deleteSize"},{"method":"PUT","route":"unit","handler":"\\App\\Controllers\\Home::unit"},{"method":"PUT","route":"saveUnit","handler":"\\App\\Controllers\\Home::saveUnit"},{"method":"PUT","route":"deleteUnit","handler":"\\App\\Controllers\\Home::deleteUnit"},{"method":"PUT","route":"sizeUnit","handler":"\\App\\Controllers\\Home::sizeUnit"},{"method":"PUT","route":"updateUnitSizeAuto","handler":"\\App\\Controllers\\Home::updateUnitSizeAuto"},{"method":"PUT","route":"transaction","handler":"\\App\\Controllers\\Home::transaction"},{"method":"PUT","route":"saveTransaction","handler":"\\App\\Controllers\\Home::saveTransaction"},{"method":"PUT","route":"deleteTransaction","handler":"\\App\\Controllers\\Home::deleteTransaction"},{"method":"PUT","route":"reports","handler":"\\App\\Controllers\\Home::reports"},{"method":"PUT","route":"imports","handler":"\\App\\Controllers\\Home::imports"},{"method":"DELETE","route":"getDataToAddForm","handler":"\\App\\Controllers\\Home::getDataToAddForm"},{"method":"DELETE","route":"getDetailDataToAdd","handler":"\\App\\Controllers\\Home::getDetailDataToAdd"},{"method":"DELETE","route":"getAreaId","handler":"\\App\\Controllers\\Home::getAreaId"},{"method":"DELETE","route":"getFoodPrice","handler":"\\App\\Controllers\\Home::getFoodPrice"},{"method":"DELETE","route":"saveOrder","handler":"\\App\\Controllers\\Home::saveOrder"},{"method":"DELETE","route":"saveMainOrder","handler":"\\App\\Controllers\\Home::saveMainOrder"},{"method":"DELETE","route":"deleteMainOrder","handler":"\\App\\Controllers\\Home::deleteMainOrder"},{"method":"DELETE","route":"saveDetail","handler":"\\App\\Controllers\\Home::saveDetail"},{"method":"DELETE","route":"deleteDetail","handler":"\\App\\Controllers\\Home::deleteDetail"},{"method":"DELETE","route":"printer","handler":"\\App\\Controllers\\Home::printer"},{"method":"DELETE","route":"area","handler":"\\App\\Controllers\\Home::area"},{"method":"DELETE","route":"saveArea","handler":"\\App\\Controllers\\Home::saveArea"},{"method":"DELETE","route":"deleteArea","handler":"\\App\\Controllers\\Home::deleteArea"},{"method":"DELETE","route":"tableOrder","handler":"\\App\\Controllers\\Home::tableOrder"},{"method":"DELETE","route":"saveTableOrder","handler":"\\App\\Controllers\\Home::saveTableOrder"},{"method":"DELETE","route":"deleteTableOrder","handler":"\\App\\Controllers\\Home::deleteTableOrder"},{"method":"DELETE","route":"food","handler":"\\App\\Controllers\\Home::food"},{"method":"DELETE","route":"saveFood","handler":"\\App\\Controllers\\Home::saveFood"},{"method":"DELETE","route":"deleteFood","handler":"\\App\\Controllers\\Home::deleteFood"},{"method":"DELETE","route":"promotion","handler":"\\App\\Controllers\\Home::promotion"},{"method":"DELETE","route":"savePromotion","handler":"\\App\\Controllers\\Home::savePromotion"},{"method":"DELETE","route":"deletePromotion","handler":"\\App\\Controllers\\Home::deletePromotion"},{"method":"DELETE","route":"size","handler":"\\App\\Controllers\\Home::size"},{"method":"DELETE","route":"saveSize","handler":"\\App\\Controllers\\Home::saveSize"},{"method":"DELETE","route":"deleteSize","handler":"\\App\\Controllers\\Home::deleteSize"},{"method":"DELETE","route":"unit","handler":"\\App\\Controllers\\Home::unit"},{"method":"DELETE","route":"saveUnit","handler":"\\App\\Controllers\\Home::saveUnit"},{"method":"DELETE","route":"deleteUnit","handler":"\\App\\Controllers\\Home::deleteUnit"},{"method":"DELETE","route":"sizeUnit","handler":"\\App\\Controllers\\Home::sizeUnit"},{"method":"DELETE","route":"updateUnitSizeAuto","handler":"\\App\\Controllers\\Home::updateUnitSizeAuto"},{"method":"DELETE","route":"transaction","handler":"\\App\\Controllers\\Home::transaction"},{"method":"DELETE","route":"saveTransaction","handler":"\\App\\Controllers\\Home::saveTransaction"},{"method":"DELETE","route":"deleteTransaction","handler":"\\App\\Controllers\\Home::deleteTransaction"},{"method":"DELETE","route":"reports","handler":"\\App\\Controllers\\Home::reports"},{"method":"DELETE","route":"imports","handler":"\\App\\Controllers\\Home::imports"},{"method":"OPTIONS","route":"getDataToAddForm","handler":"\\App\\Controllers\\Home::getDataToAddForm"},{"method":"OPTIONS","route":"getDetailDataToAdd","handler":"\\App\\Controllers\\Home::getDetailDataToAdd"},{"method":"OPTIONS","route":"getAreaId","handler":"\\App\\Controllers\\Home::getAreaId"},{"method":"OPTIONS","route":"getFoodPrice","handler":"\\App\\Controllers\\Home::getFoodPrice"},{"method":"OPTIONS","route":"saveOrder","handler":"\\App\\Controllers\\Home::saveOrder"},{"method":"OPTIONS","route":"saveMainOrder","handler":"\\App\\Controllers\\Home::saveMainOrder"},{"method":"OPTIONS","route":"deleteMainOrder","handler":"\\App\\Controllers\\Home::deleteMainOrder"},{"method":"OPTIONS","route":"saveDetail","handler":"\\App\\Controllers\\Home::saveDetail"},{"method":"OPTIONS","route":"deleteDetail","handler":"\\App\\Controllers\\Home::deleteDetail"},{"method":"OPTIONS","route":"printer","handler":"\\App\\Controllers\\Home::printer"},{"method":"OPTIONS","route":"area","handler":"\\App\\Controllers\\Home::area"},{"method":"OPTIONS","route":"saveArea","handler":"\\App\\Controllers\\Home::saveArea"},{"method":"OPTIONS","route":"deleteArea","handler":"\\App\\Controllers\\Home::deleteArea"},{"method":"OPTIONS","route":"tableOrder","handler":"\\App\\Controllers\\Home::tableOrder"},{"method":"OPTIONS","route":"saveTableOrder","handler":"\\App\\Controllers\\Home::saveTableOrder"},{"method":"OPTIONS","route":"deleteTableOrder","handler":"\\App\\Controllers\\Home::deleteTableOrder"},{"method":"OPTIONS","route":"food","handler":"\\App\\Controllers\\Home::food"},{"method":"OPTIONS","route":"saveFood","handler":"\\App\\Controllers\\Home::saveFood"},{"method":"OPTIONS","route":"deleteFood","handler":"\\App\\Controllers\\Home::deleteFood"},{"method":"OPTIONS","route":"promotion","handler":"\\App\\Controllers\\Home::promotion"},{"method":"OPTIONS","route":"savePromotion","handler":"\\App\\Controllers\\Home::savePromotion"},{"method":"OPTIONS","route":"deletePromotion","handler":"\\App\\Controllers\\Home::deletePromotion"},{"method":"OPTIONS","route":"size","handler":"\\App\\Controllers\\Home::size"},{"method":"OPTIONS","route":"saveSize","handler":"\\App\\Controllers\\Home::saveSize"},{"method":"OPTIONS","route":"deleteSize","handler":"\\App\\Controllers\\Home::deleteSize"},{"method":"OPTIONS","route":"unit","handler":"\\App\\Controllers\\Home::unit"},{"method":"OPTIONS","route":"saveUnit","handler":"\\App\\Controllers\\Home::saveUnit"},{"method":"OPTIONS","route":"deleteUnit","handler":"\\App\\Controllers\\Home::deleteUnit"},{"method":"OPTIONS","route":"sizeUnit","handler":"\\App\\Controllers\\Home::sizeUnit"},{"method":"OPTIONS","route":"updateUnitSizeAuto","handler":"\\App\\Controllers\\Home::updateUnitSizeAuto"},{"method":"OPTIONS","route":"transaction","handler":"\\App\\Controllers\\Home::transaction"},{"method":"OPTIONS","route":"saveTransaction","handler":"\\App\\Controllers\\Home::saveTransaction"},{"method":"OPTIONS","route":"deleteTransaction","handler":"\\App\\Controllers\\Home::deleteTransaction"},{"method":"OPTIONS","route":"reports","handler":"\\App\\Controllers\\Home::reports"},{"method":"OPTIONS","route":"imports","handler":"\\App\\Controllers\\Home::imports"},{"method":"TRACE","route":"getDataToAddForm","handler":"\\App\\Controllers\\Home::getDataToAddForm"},{"method":"TRACE","route":"getDetailDataToAdd","handler":"\\App\\Controllers\\Home::getDetailDataToAdd"},{"method":"TRACE","route":"getAreaId","handler":"\\App\\Controllers\\Home::getAreaId"},{"method":"TRACE","route":"getFoodPrice","handler":"\\App\\Controllers\\Home::getFoodPrice"},{"method":"TRACE","route":"saveOrder","handler":"\\App\\Controllers\\Home::saveOrder"},{"method":"TRACE","route":"saveMainOrder","handler":"\\App\\Controllers\\Home::saveMainOrder"},{"method":"TRACE","route":"deleteMainOrder","handler":"\\App\\Controllers\\Home::deleteMainOrder"},{"method":"TRACE","route":"saveDetail","handler":"\\App\\Controllers\\Home::saveDetail"},{"method":"TRACE","route":"deleteDetail","handler":"\\App\\Controllers\\Home::deleteDetail"},{"method":"TRACE","route":"printer","handler":"\\App\\Controllers\\Home::printer"},{"method":"TRACE","route":"area","handler":"\\App\\Controllers\\Home::area"},{"method":"TRACE","route":"saveArea","handler":"\\App\\Controllers\\Home::saveArea"},{"method":"TRACE","route":"deleteArea","handler":"\\App\\Controllers\\Home::deleteArea"},{"method":"TRACE","route":"tableOrder","handler":"\\App\\Controllers\\Home::tableOrder"},{"method":"TRACE","route":"saveTableOrder","handler":"\\App\\Controllers\\Home::saveTableOrder"},{"method":"TRACE","route":"deleteTableOrder","handler":"\\App\\Controllers\\Home::deleteTableOrder"},{"method":"TRACE","route":"food","handler":"\\App\\Controllers\\Home::food"},{"method":"TRACE","route":"saveFood","handler":"\\App\\Controllers\\Home::saveFood"},{"method":"TRACE","route":"deleteFood","handler":"\\App\\Controllers\\Home::deleteFood"},{"method":"TRACE","route":"promotion","handler":"\\App\\Controllers\\Home::promotion"},{"method":"TRACE","route":"savePromotion","handler":"\\App\\Controllers\\Home::savePromotion"},{"method":"TRACE","route":"deletePromotion","handler":"\\App\\Controllers\\Home::deletePromotion"},{"method":"TRACE","route":"size","handler":"\\App\\Controllers\\Home::size"},{"method":"TRACE","route":"saveSize","handler":"\\App\\Controllers\\Home::saveSize"},{"method":"TRACE","route":"deleteSize","handler":"\\App\\Controllers\\Home::deleteSize"},{"method":"TRACE","route":"unit","handler":"\\App\\Controllers\\Home::unit"},{"method":"TRACE","route":"saveUnit","handler":"\\App\\Controllers\\Home::saveUnit"},{"method":"TRACE","route":"deleteUnit","handler":"\\App\\Controllers\\Home::deleteUnit"},{"method":"TRACE","route":"sizeUnit","handler":"\\App\\Controllers\\Home::sizeUnit"},{"method":"TRACE","route":"updateUnitSizeAuto","handler":"\\App\\Controllers\\Home::updateUnitSizeAuto"},{"method":"TRACE","route":"transaction","handler":"\\App\\Controllers\\Home::transaction"},{"method":"TRACE","route":"saveTransaction","handler":"\\App\\Controllers\\Home::saveTransaction"},{"method":"TRACE","route":"deleteTransaction","handler":"\\App\\Controllers\\Home::deleteTransaction"},{"method":"TRACE","route":"reports","handler":"\\App\\Controllers\\Home::reports"},{"method":"TRACE","route":"imports","handler":"\\App\\Controllers\\Home::imports"},{"method":"CONNECT","route":"getDataToAddForm","handler":"\\App\\Controllers\\Home::getDataToAddForm"},{"method":"CONNECT","route":"getDetailDataToAdd","handler":"\\App\\Controllers\\Home::getDetailDataToAdd"},{"method":"CONNECT","route":"getAreaId","handler":"\\App\\Controllers\\Home::getAreaId"},{"method":"CONNECT","route":"getFoodPrice","handler":"\\App\\Controllers\\Home::getFoodPrice"},{"method":"CONNECT","route":"saveOrder","handler":"\\App\\Controllers\\Home::saveOrder"},{"method":"CONNECT","route":"saveMainOrder","handler":"\\App\\Controllers\\Home::saveMainOrder"},{"method":"CONNECT","route":"deleteMainOrder","handler":"\\App\\Controllers\\Home::deleteMainOrder"},{"method":"CONNECT","route":"saveDetail","handler":"\\App\\Controllers\\Home::saveDetail"},{"method":"CONNECT","route":"deleteDetail","handler":"\\App\\Controllers\\Home::deleteDetail"},{"method":"CONNECT","route":"printer","handler":"\\App\\Controllers\\Home::printer"},{"method":"CONNECT","route":"area","handler":"\\App\\Controllers\\Home::area"},{"method":"CONNECT","route":"saveArea","handler":"\\App\\Controllers\\Home::saveArea"},{"method":"CONNECT","route":"deleteArea","handler":"\\App\\Controllers\\Home::deleteArea"},{"method":"CONNECT","route":"tableOrder","handler":"\\App\\Controllers\\Home::tableOrder"},{"method":"CONNECT","route":"saveTableOrder","handler":"\\App\\Controllers\\Home::saveTableOrder"},{"method":"CONNECT","route":"deleteTableOrder","handler":"\\App\\Controllers\\Home::deleteTableOrder"},{"method":"CONNECT","route":"food","handler":"\\App\\Controllers\\Home::food"},{"method":"CONNECT","route":"saveFood","handler":"\\App\\Controllers\\Home::saveFood"},{"method":"CONNECT","route":"deleteFood","handler":"\\App\\Controllers\\Home::deleteFood"},{"method":"CONNECT","route":"promotion","handler":"\\App\\Controllers\\Home::promotion"},{"method":"CONNECT","route":"savePromotion","handler":"\\App\\Controllers\\Home::savePromotion"},{"method":"CONNECT","route":"deletePromotion","handler":"\\App\\Controllers\\Home::deletePromotion"},{"method":"CONNECT","route":"size","handler":"\\App\\Controllers\\Home::size"},{"method":"CONNECT","route":"saveSize","handler":"\\App\\Controllers\\Home::saveSize"},{"method":"CONNECT","route":"deleteSize","handler":"\\App\\Controllers\\Home::deleteSize"},{"method":"CONNECT","route":"unit","handler":"\\App\\Controllers\\Home::unit"},{"method":"CONNECT","route":"saveUnit","handler":"\\App\\Controllers\\Home::saveUnit"},{"method":"CONNECT","route":"deleteUnit","handler":"\\App\\Controllers\\Home::deleteUnit"},{"method":"CONNECT","route":"sizeUnit","handler":"\\App\\Controllers\\Home::sizeUnit"},{"method":"CONNECT","route":"updateUnitSizeAuto","handler":"\\App\\Controllers\\Home::updateUnitSizeAuto"},{"method":"CONNECT","route":"transaction","handler":"\\App\\Controllers\\Home::transaction"},{"method":"CONNECT","route":"saveTransaction","handler":"\\App\\Controllers\\Home::saveTransaction"},{"method":"CONNECT","route":"deleteTransaction","handler":"\\App\\Controllers\\Home::deleteTransaction"},{"method":"CONNECT","route":"reports","handler":"\\App\\Controllers\\Home::reports"},{"method":"CONNECT","route":"imports","handler":"\\App\\Controllers\\Home::imports"},{"method":"CLI","route":"getDataToAddForm","handler":"\\App\\Controllers\\Home::getDataToAddForm"},{"method":"CLI","route":"getDetailDataToAdd","handler":"\\App\\Controllers\\Home::getDetailDataToAdd"},{"method":"CLI","route":"getAreaId","handler":"\\App\\Controllers\\Home::getAreaId"},{"method":"CLI","route":"getFoodPrice","handler":"\\App\\Controllers\\Home::getFoodPrice"},{"method":"CLI","route":"saveOrder","handler":"\\App\\Controllers\\Home::saveOrder"},{"method":"CLI","route":"saveMainOrder","handler":"\\App\\Controllers\\Home::saveMainOrder"},{"method":"CLI","route":"deleteMainOrder","handler":"\\App\\Controllers\\Home::deleteMainOrder"},{"method":"CLI","route":"saveDetail","handler":"\\App\\Controllers\\Home::saveDetail"},{"method":"CLI","route":"deleteDetail","handler":"\\App\\Controllers\\Home::deleteDetail"},{"method":"CLI","route":"printer","handler":"\\App\\Controllers\\Home::printer"},{"method":"CLI","route":"area","handler":"\\App\\Controllers\\Home::area"},{"method":"CLI","route":"saveArea","handler":"\\App\\Controllers\\Home::saveArea"},{"method":"CLI","route":"deleteArea","handler":"\\App\\Controllers\\Home::deleteArea"},{"method":"CLI","route":"tableOrder","handler":"\\App\\Controllers\\Home::tableOrder"},{"method":"CLI","route":"saveTableOrder","handler":"\\App\\Controllers\\Home::saveTableOrder"},{"method":"CLI","route":"deleteTableOrder","handler":"\\App\\Controllers\\Home::deleteTableOrder"},{"method":"CLI","route":"food","handler":"\\App\\Controllers\\Home::food"},{"method":"CLI","route":"saveFood","handler":"\\App\\Controllers\\Home::saveFood"},{"method":"CLI","route":"deleteFood","handler":"\\App\\Controllers\\Home::deleteFood"},{"method":"CLI","route":"promotion","handler":"\\App\\Controllers\\Home::promotion"},{"method":"CLI","route":"savePromotion","handler":"\\App\\Controllers\\Home::savePromotion"},{"method":"CLI","route":"deletePromotion","handler":"\\App\\Controllers\\Home::deletePromotion"},{"method":"CLI","route":"size","handler":"\\App\\Controllers\\Home::size"},{"method":"CLI","route":"saveSize","handler":"\\App\\Controllers\\Home::saveSize"},{"method":"CLI","route":"deleteSize","handler":"\\App\\Controllers\\Home::deleteSize"},{"method":"CLI","route":"unit","handler":"\\App\\Controllers\\Home::unit"},{"method":"CLI","route":"saveUnit","handler":"\\App\\Controllers\\Home::saveUnit"},{"method":"CLI","route":"deleteUnit","handler":"\\App\\Controllers\\Home::deleteUnit"},{"method":"CLI","route":"sizeUnit","handler":"\\App\\Controllers\\Home::sizeUnit"},{"method":"CLI","route":"updateUnitSizeAuto","handler":"\\App\\Controllers\\Home::updateUnitSizeAuto"},{"method":"CLI","route":"transaction","handler":"\\App\\Controllers\\Home::transaction"},{"method":"CLI","route":"saveTransaction","handler":"\\App\\Controllers\\Home::saveTransaction"},{"method":"CLI","route":"deleteTransaction","handler":"\\App\\Controllers\\Home::deleteTransaction"},{"method":"CLI","route":"reports","handler":"\\App\\Controllers\\Home::reports"},{"method":"CLI","route":"imports","handler":"\\App\\Controllers\\Home::imports"}]},"badgeValue":35,"isEmpty":false,"hasTabContent":true,"hasLabel":false,"icon":"data:image\/png;base64,iVBORw0KGgoAAAANSUhEUgAAABgAAAAYCAYAAADgdz34AAAAAXNSR0IArs4c6QAAAARnQU1BAACxjwv8YQUAAAAJcEhZcwAADsMAAA7DAcdvqGQAAAFDSURBVEhL7ZRNSsNQFIUjVXSiOFEcuQIHDpzpxC0IGYeE\/BEInbWlCHEDLsSiuANdhKDjgm6ggtSJ+l25ldrmmTwIgtgDh\/t37r1J+16cX0dRFMtpmu5pWAkrvYjjOB7AETzStBFW+inxu3KUJMmhludQpoflS1zXban4LYqiO224h6VLTHr8Z+z8EpIHFF9gG78nDVmW7UgTHKjsCyY98QP+pcq+g8Ku2s8G8X3f3\/I8b038WZTp+bO38zxfFd+I6YY6sNUvFlSDk9CRhiAI1jX1I9Cfw7GG1UB8LAuwbU0ZwQnbRDeEN5qqBxZMLtE1ti9LtbREnMIuOXnyIf5rGIb7Wq8HmlZgwYBH7ORTcKH5E4mpjeGt9fBZcHE2GCQ3Vt7oTNPNg+FXLHnSsHkw\/FR+Gg2bB8Ptzrst\/v6C\/wrH+QB+duli6MYJdQAAAABJRU5ErkJggg==","hasTimelineData":false,"timelineData":[]},{"title":"Events","titleSafe":"events","titleDetails":"","display":{"events":{"pre_system":{"event":"pre_system","duration":"5.31","count":1},"dbquery":{"event":"dbquery","duration":"0.29","count":24}}},"badgeValue":25,"isEmpty":false,"hasTabContent":true,"hasLabel":false,"icon":"data:image\/png;base64,iVBORw0KGgoAAAANSUhEUgAAABgAAAAYCAYAAADgdz34AAAAAXNSR0IArs4c6QAAAARnQU1BAACxjwv8YQUAAAAJcEhZcwAADsMAAA7DAcdvqGQAAAEASURBVEhL7ZXNDcIwDIVTsRBH1uDQDdquUA6IM1xgCA6MwJUN2hk6AQzAz0vl0ETUxC5VT3zSU5w81\/mRMGZysixbFEVR0jSKNt8geQU9aRpFmp\/keX6AbjZ5oB74vsaN5lSzA4tLSjpBFxsjeSuRy4d2mDdQTWU7YLbXTNN05mKyovj5KL6B7q3hoy3KwdZxBlT+Ipz+jPHrBqOIynZgcZonoukb\/0ckiTHqNvDXtXEAaygRbaB9FvUTjRUHsIYS0QaSp+Dw6wT4hiTmYHOcYZsdLQ2CbXa4ftuuYR4x9vYZgdb4vsFYUdmABMYeukK9\/SUme3KMFQ77+Yfzh8eYF8+orDuDWU5LAAAAAElFTkSuQmCC","hasTimelineData":true,"timelineData":[{"name":"Event: pre_system","component":"Events","start":1697704245.210049,"duration":0.0053060054779052734},{"name":"Event: dbquery","component":"Events","start":1697704245.274472,"duration":2.5033950805664062e-5},{"name":"Event: dbquery","component":"Events","start":1697704245.275914,"duration":1.4066696166992188e-5},{"name":"Event: dbquery","component":"Events","start":1697704245.276159,"duration":1.4066696166992188e-5},{"name":"Event: dbquery","component":"Events","start":1697704245.276441,"duration":1.1920928955078125e-5},{"name":"Event: dbquery","component":"Events","start":1697704245.276694,"duration":1.0967254638671875e-5},{"name":"Event: dbquery","component":"Events","start":1697704245.276953,"duration":1.1920928955078125e-5},{"name":"Event: dbquery","component":"Events","start":1697704245.277206,"duration":1.2159347534179688e-5},{"name":"Event: dbquery","component":"Events","start":1697704245.277513,"duration":1.1920928955078125e-5},{"name":"Event: dbquery","component":"Events","start":1697704245.277785,"duration":1.2874603271484375e-5},{"name":"Event: dbquery","component":"Events","start":1697704245.278073,"duration":1.2874603271484375e-5},{"name":"Event: dbquery","component":"Events","start":1697704245.278287,"duration":1.2159347534179688e-5},{"name":"Event: dbquery","component":"Events","start":1697704245.278485,"duration":1.1920928955078125e-5},{"name":"Event: dbquery","component":"Events","start":1697704245.278667,"duration":1.1920928955078125e-5},{"name":"Event: dbquery","component":"Events","start":1697704245.278887,"duration":1.0013580322265625e-5},{"name":"Event: dbquery","component":"Events","start":1697704245.279087,"duration":1.0967254638671875e-5},{"name":"Event: dbquery","component":"Events","start":1697704245.279321,"duration":1.0967254638671875e-5},{"name":"Event: dbquery","component":"Events","start":1697704245.27955,"duration":1.1920928955078125e-5},{"name":"Event: dbquery","component":"Events","start":1697704245.279764,"duration":1.0967254638671875e-5},{"name":"Event: dbquery","component":"Events","start":1697704245.279953,"duration":1.0013580322265625e-5},{"name":"Event: dbquery","component":"Events","start":1697704245.280123,"duration":1.0013580322265625e-5},{"name":"Event: dbquery","component":"Events","start":1697704245.280296,"duration":8.821487426757812e-6},{"name":"Event: dbquery","component":"Events","start":1697704245.280463,"duration":1.1920928955078125e-5},{"name":"Event: dbquery","component":"Events","start":1697704245.280661,"duration":9.775161743164062e-6},{"name":"Event: dbquery","component":"Events","start":1697704245.280829,"duration":1.0013580322265625e-5}]}],"vars":{"varData":{"View Data":[]},"post":{"data":"{&quot;type&quot;:&quot;daily&quot;,&quot;from_date&quot;:null,&quot;to_date&quot;:null}"},"headers":{"Content-Type":"application\/x-www-form-urlencoded; charset=UTF-8","Host":"localhost:8080","Connection":"keep-alive","Sec-Ch-Ua":"&quot;Chromium&quot;;v=&quot;118&quot;, &quot;Google Chrome&quot;;v=&quot;118&quot;, &quot;Not=A?Brand&quot;;v=&quot;99&quot;","Accept":"*\/*","X-Requested-With":"XMLHttpRequest","Sec-Ch-Ua-Mobile":"?0","User-Agent":"Mozilla\/5.0 (Windows NT 10.0; Win64; x64) AppleWebKit\/537.36 (KHTML, like Gecko) Chrome\/118.0.0.0 Safari\/537.36","Sec-Ch-Ua-Platform":"&quot;Windows&quot;","Origin":"http:\/\/localhost:8080","Sec-Fetch-Site":"same-origin","Sec-Fetch-Mode":"cors","Sec-Fetch-Dest":"empty","Referer":"http:\/\/localhost:8080\/babana\/","Accept-Encoding":"gzip, deflate, br","Accept-Language":"en-US,en;q=0.9,vi;q=0.8"},"request":"HTTP\/1.1","response":{"statusCode":200,"reason":"OK","contentType":"text\/html; charset=UTF-8","headers":{"Cache-Control":"no-store, max-age=0, no-cache","Content-Type":"text\/html; charset=UTF-8"}}},"config":{"ciVersion":"4.3.7","phpVersion":"8.0.28","phpSAPI":"apache2handler","environment":"development","baseURL":"http:\/\/localhost:8080\/babana\/","timezone":"UTC","locale":"en","cspEnabled":false}}